[{"id":1,"car_make":"Chevrolet","car_model":"Express 1500","year":2000,"vin":"1G6DJ5EG1A0214971"},
{"id":2,"car_make":"Infiniti","car_model":"FX","year":2006,"vin":"JTDKN3DU8A0643321"},
{"id":3,"car_make":"Lexus","car_model":"GS","year":2009,"vin":"1G6KF54952U574749"},
{"id":4,"car_make":"Jeep","car_model":"Patriot","year":2007,"vin":"KMHEC4A44DA477452"},
{"id":5,"car_make":"Volkswagen","car_model":"Eurovan","year":1999,"vin":"5XYZT3LB4DG389853"},
{"id":6,"car_make":"Hyundai","car_model":"Azera","year":2006,"vin":"5XYKT3A67EG686253"},
{"id":7,"car_make":"Toyota","car_model":"RAV4","year":1996,"vin":"1GD21ZCG4BZ058805"},
{"id":8,"car_make":"Hyundai","car_model":"Genesis","year":2012,"vin":"WAUGU54DX1N618215"},
{"id":9,"car_make":"Volkswagen","car_model":"GTI","year":1998,"vin":"1GYFK63868R101439"},
{"id":10,"car_make":"Chevrolet","car_model":"Avalanche","year":2002,"vin":"WAUHFAFL6AN231351"},
{"id":11,"car_make":"Oldsmobile","car_model":"Bravada","year":2003,"vin":"JHMZE2H33CS939198"},
{"id":12,"car_make":"Lotus","car_model":"Exige","year":2012,"vin":"WA1WMAFE0CD128267"},
{"id":13,"car_make":"Dodge","car_model":"Shadow","year":1992,"vin":"KMHHT6KD7EU547842"},
{"id":14,"car_make":"Lexus","car_model":"RX","year":2011,"vin":"5UXXW3C56F0577919"},
{"id":15,"car_make":"Lexus","car_model":"GX","year":2006,"vin":"5N1AA0NE6EN244568"},
{"id":16,"car_make":"GMC","car_model":"Yukon","year":2013,"vin":"WBA3D5C50FK566563"},
{"id":17,"car_make":"Suzuki","car_model":"XL-7","year":2008,"vin":"3GYFK66NX5G397384"},
{"id":18,"car_make":"Hummer","car_model":"H3","year":2009,"vin":"WBAVC73547K480584"},
{"id":19,"car_make":"Chevrolet","car_model":"Avalanche","year":2002,"vin":"WAUGN74F69N165653"},
{"id":20,"car_make":"Infiniti","car_model":"QX","year":1997,"vin":"1D4PT4GK1AW614917"},
{"id":21,"car_make":"Aston Martin","car_model":"DB9","year":2007,"vin":"1N6AA0CC7EN021460"},
{"id":22,"car_make":"Audi","car_model":"5000S","year":1987,"vin":"WBASN4C53AC030826"},
{"id":23,"car_make":"Chrysler","car_model":"PT Cruiser","year":2006,"vin":"1FTEW1CM5CK885388"},
{"id":24,"car_make":"Ford","car_model":"Expedition","year":2011,"vin":"JN1BJ0HP1DM106546"},
{"id":25,"car_make":"GMC","car_model":"3500","year":1999,"vin":"3C6TD5JT7CG502499"},
{"id":26,"car_make":"GMC","car_model":"3500","year":1999,"vin":"1N4AA5AP7BC713513"},
{"id":27,"car_make":"Ford","car_model":"Crown Victoria","year":1995,"vin":"WBAET37474N156310"},
{"id":28,"car_make":"Chevrolet","car_model":"Suburban 2500","year":1996,"vin":"1GYEK63NX5R632611"},
{"id":29,"car_make":"Ford","car_model":"Mustang","year":1990,"vin":"JTEBW3EH1A2957035"},
{"id":30,"car_make":"Chevrolet","car_model":"1500","year":1993,"vin":"19UYA424X1A378945"},
{"id":31,"car_make":"Plymouth","car_model":"Reliant","year":1981,"vin":"JTDKTUD33ED887847"},
{"id":32,"car_make":"Nissan","car_model":"Xterra","year":2012,"vin":"WP0AA2A97ES852447"},
{"id":33,"car_make":"Land Rover","car_model":"Range Rover Sport","year":2010,"vin":"WAUVC58E12A171750"},
{"id":34,"car_make":"Ford","car_model":"Bronco","year":1984,"vin":"WAUFL54D81N870740"},
{"id":35,"car_make":"Toyota","car_model":"Prius","year":2011,"vin":"WAUDF48H19K009144"},
{"id":36,"car_make":"Lincoln","car_model":"Continental","year":1994,"vin":"1G6DA5EG2A0824023"},
{"id":37,"car_make":"Buick","car_model":"Century","year":1995,"vin":"1FTEX1CM1BF529895"},
{"id":38,"car_make":"BMW","car_model":"M3","year":2005,"vin":"5BZBF0AA0FN539809"},
{"id":39,"car_make":"Plymouth","car_model":"Neon","year":1997,"vin":"WAUBFAFL7AA672080"},
{"id":40,"car_make":"Pontiac","car_model":"Grand Prix","year":1966,"vin":"1G6AB5RA5E0041371"},
{"id":41,"car_make":"Eagle","car_model":"Premier","year":1992,"vin":"5TDBW5G12BS944417"},
{"id":42,"car_make":"BMW","car_model":"760","year":2003,"vin":"1FMJK1HT1FE591317"},
{"id":43,"car_make":"Jaguar","car_model":"X-Type","year":2002,"vin":"SCFAB01A88G823186"},
{"id":44,"car_make":"Volvo","car_model":"V40","year":2002,"vin":"WAUPFAFM6BA598618"},
{"id":45,"car_make":"BMW","car_model":"X6","year":2008,"vin":"SCBLC31E61C589834"},
{"id":46,"car_make":"Buick","car_model":"Skylark","year":1995,"vin":"WDDGF4HB5CF881439"},
{"id":47,"car_make":"Jeep","car_model":"Grand Cherokee","year":1997,"vin":"YV4952CY8C1508329"},
{"id":48,"car_make":"Audi","car_model":"A6","year":2005,"vin":"WVGEP9BP5FD003683"},
{"id":49,"car_make":"Mazda","car_model":"CX-9","year":2008,"vin":"1FTSF3A51AE254241"},
{"id":50,"car_make":"GMC","car_model":"Sierra 2500","year":2005,"vin":"JA4AP3AU0CZ000514"},
{"id":51,"car_make":"Lincoln","car_model":"Mark LT","year":2007,"vin":"JN1AY1APXDM001592"},
{"id":52,"car_make":"Pontiac","car_model":"Firefly","year":1985,"vin":"2G4WC582281893711"},
{"id":53,"car_make":"BMW","car_model":"X6","year":2012,"vin":"5N1AN0NW0DN161780"},
{"id":54,"car_make":"Jeep","car_model":"Wrangler","year":2010,"vin":"3D73Y4HL5BG094960"},
{"id":55,"car_make":"Mitsubishi","car_model":"Galant","year":2003,"vin":"WBA3C3C50FP486965"},
{"id":56,"car_make":"BMW","car_model":"M3","year":1996,"vin":"WAUVFAFR3AA334886"},
{"id":57,"car_make":"Ford","car_model":"Escort","year":1986,"vin":"1ZVBP8AM5B5200525"},
{"id":58,"car_make":"Chevrolet","car_model":"3500","year":1999,"vin":"1C4RJEAG5FC806095"},
{"id":59,"car_make":"Isuzu","car_model":"Trooper","year":1994,"vin":"WAUUL98E06A638746"},
{"id":60,"car_make":"Porsche","car_model":"Cayman","year":2006,"vin":"5TDDK3DC2DS706178"},
{"id":61,"car_make":"Dodge","car_model":"Caravan","year":1995,"vin":"1GD422CG4EF704895"},
{"id":62,"car_make":"Buick","car_model":"Century","year":1985,"vin":"JM1NC2JFXF0349283"},
{"id":63,"car_make":"Porsche","car_model":"911","year":1992,"vin":"1HGCP2E37AA502024"},
{"id":64,"car_make":"Chevrolet","car_model":"Silverado 1500","year":2007,"vin":"WUAAU34268N429344"},
{"id":65,"car_make":"Toyota","car_model":"Highlander","year":2005,"vin":"WAUHFAFL9AA799570"},
{"id":66,"car_make":"Kia","car_model":"Sportage","year":1999,"vin":"KMHTC6AD1DU572228"},
{"id":67,"car_make":"Mitsubishi","car_model":"Cordia","year":1984,"vin":"2C3CA4CG5BH396990"},
{"id":68,"car_make":"Plymouth","car_model":"Acclaim","year":1994,"vin":"4T1BF1FK6CU548227"},
{"id":69,"car_make":"Cadillac","car_model":"CTS-V","year":2009,"vin":"TRURD38J791735002"},
{"id":70,"car_make":"BMW","car_model":"X6 M","year":2011,"vin":"WBANB33524B129325"},
{"id":71,"car_make":"Mercury","car_model":"Cougar","year":1995,"vin":"KNADH4A30A6375974"},
{"id":72,"car_make":"GMC","car_model":"3500","year":1998,"vin":"WBSBR93454P572978"},
{"id":73,"car_make":"Mercedes-Benz","car_model":"S-Class","year":2009,"vin":"SALME1D40CA100080"},
{"id":74,"car_make":"Mitsubishi","car_model":"Pajero","year":1990,"vin":"19UUB2F39FA127715"},
{"id":75,"car_make":"BMW","car_model":"X5","year":2006,"vin":"1G4GC5EC6BF149322"},
{"id":76,"car_make":"Mitsubishi","car_model":"3000GT","year":1992,"vin":"WBABS53423E248379"},
{"id":77,"car_make":"Dodge","car_model":"Neon","year":1996,"vin":"SAJWA4HA0EM306662"},
{"id":78,"car_make":"Dodge","car_model":"Viper","year":1999,"vin":"1C3CCBABXCN723933"},
{"id":79,"car_make":"Ford","car_model":"Thunderbird","year":1965,"vin":"1G6DK8E38C0358970"},
{"id":80,"car_make":"GMC","car_model":"Yukon","year":1992,"vin":"JN1BJ0HP3EM437923"},
{"id":81,"car_make":"Lincoln","car_model":"MKT","year":2012,"vin":"WAUEH64B01N036009"},
{"id":82,"car_make":"Toyota","car_model":"Xtra","year":1992,"vin":"WBANE73586B039419"},
{"id":83,"car_make":"Ford","car_model":"Ranger","year":1989,"vin":"KNDPB3A23C7408403"},
{"id":84,"car_make":"Honda","car_model":"Prelude","year":2000,"vin":"1FMJU1K50AE538394"},
{"id":85,"car_make":"Honda","car_model":"Civic","year":2006,"vin":"3VW467AT3DM592544"},
{"id":86,"car_make":"Chevrolet","car_model":"Camaro","year":1995,"vin":"2G61U5S37D9683682"},
{"id":87,"car_make":"Volkswagen","car_model":"Passat","year":2000,"vin":"KMHHT6KD5AU775185"},
{"id":88,"car_make":"Acura","car_model":"Integra","year":1998,"vin":"WAUDL94F96N815513"},
{"id":89,"car_make":"Audi","car_model":"Allroad","year":2005,"vin":"5YMGY0C57CL154052"},
{"id":90,"car_make":"Dodge","car_model":"Viper","year":1994,"vin":"1FTEX1EW2AK272508"},
{"id":91,"car_make":"Pontiac","car_model":"Grand Prix","year":1980,"vin":"WAUFEBFM4CA592631"},
{"id":92,"car_make":"Mercedes-Benz","car_model":"SLR McLaren","year":2008,"vin":"1C4RDHAG3EC811108"},
{"id":93,"car_make":"Hyundai","car_model":"Genesis Coupe","year":2013,"vin":"WAULC68E53A675247"},
{"id":94,"car_make":"Daewoo","car_model":"Lanos","year":2000,"vin":"KNDJT2A11B7273960"},
{"id":95,"car_make":"Audi","car_model":"100","year":1989,"vin":"1YVHZ8BH0D5388909"},
{"id":96,"car_make":"Suzuki","car_model":"Reno","year":2005,"vin":"WA1WMBFE6CD653615"},
{"id":97,"car_make":"Isuzu","car_model":"Oasis","year":1996,"vin":"WVWED7AJ3DW171113"},
{"id":98,"car_make":"Oldsmobile","car_model":"Silhouette","year":1995,"vin":"1G6AA5RX6F0830346"},
{"id":99,"car_make":"Land Rover","car_model":"Defender","year":1992,"vin":"2FMDK4AC6AB329855"},
{"id":100,"car_make":"Chrysler","car_model":"Pacifica","year":2004,"vin":"JH4DC53026S348699"},
{"id":101,"car_make":"BMW","car_model":"X3","year":2009,"vin":"WAUDT48H06K959838"},
{"id":102,"car_make":"Dodge","car_model":"Caravan","year":2003,"vin":"YV126MEB3F1316840"},
{"id":103,"car_make":"Ford","car_model":"Crown Victoria","year":1994,"vin":"3GTU2YEJXBG964759"},
{"id":104,"car_make":"Lincoln","car_model":"Town Car","year":1993,"vin":"1D4PU4GK1BW735641"},
{"id":105,"car_make":"Audi","car_model":"S6","year":2007,"vin":"5GAER23718J893271"},
{"id":106,"car_make":"Bentley","car_model":"Continental","year":2007,"vin":"1FADP3E2XEL049663"},
{"id":107,"car_make":"Honda","car_model":"Accord","year":2002,"vin":"WBAUP7C58AV423438"},
{"id":108,"car_make":"Mercedes-Benz","car_model":"C-Class","year":1998,"vin":"JTJHY7AX8A4790767"},
{"id":109,"car_make":"Mercedes-Benz","car_model":"E-Class","year":2002,"vin":"1FMJK1F52CE199771"},
{"id":110,"car_make":"Holden","car_model":"VS Commodore","year":1997,"vin":"WA1CV74L57D293452"},
{"id":111,"car_make":"Mazda","car_model":"626","year":1989,"vin":"2G4WF551331283019"},
{"id":112,"car_make":"Eagle","car_model":"Vision","year":1994,"vin":"1D7CW5GK8AS814330"},
{"id":113,"car_make":"Honda","car_model":"Civic Si","year":2006,"vin":"JH4DC53815S013776"},
{"id":114,"car_make":"Audi","car_model":"A7","year":2012,"vin":"3D7TP2CTXBG873253"},
{"id":115,"car_make":"Acura","car_model":"NSX","year":2003,"vin":"WBAEP33482P359850"},
{"id":116,"car_make":"Ford","car_model":"Escort","year":1984,"vin":"WUARL48H29K880235"},
{"id":117,"car_make":"Audi","car_model":"S4","year":2000,"vin":"WA1LFAFPXFA598410"},
{"id":118,"car_make":"Pontiac","car_model":"Firefly","year":1987,"vin":"3VWPG3AGXAM651218"},
{"id":119,"car_make":"Hummer","car_model":"H1","year":1996,"vin":"1FMJK1G51DE713366"},
{"id":120,"car_make":"Mazda","car_model":"RX-7","year":1995,"vin":"WVWAP7ANXEE086477"},
{"id":121,"car_make":"Volkswagen","car_model":"Passat","year":1987,"vin":"WAUSH78EX8A396709"},
{"id":122,"car_make":"Mazda","car_model":"929","year":1991,"vin":"WBACK73451L568126"},
{"id":123,"car_make":"Nissan","car_model":"Sentra","year":2012,"vin":"WAUDF98E28A602597"},
{"id":124,"car_make":"Mercury","car_model":"Milan","year":2011,"vin":"1G6KY54931U567033"},
{"id":125,"car_make":"Ford","car_model":"Econoline E150","year":2000,"vin":"WAULK98K09N251017"},
{"id":126,"car_make":"Lincoln","car_model":"Town Car","year":2005,"vin":"JM1GJ1U57F1668081"},
{"id":127,"car_make":"Ford","car_model":"Mustang","year":1998,"vin":"1FTMF1CW3AK700197"},
{"id":128,"car_make":"Pontiac","car_model":"Parisienne","year":1985,"vin":"3C3CFFER5FT756249"},
{"id":129,"car_make":"Cadillac","car_model":"DeVille","year":2002,"vin":"1GYS3JEF7DR041806"},
{"id":130,"car_make":"Lamborghini","car_model":"Murciélago","year":2008,"vin":"WAUJFAFH7BN800755"},
{"id":131,"car_make":"Ford","car_model":"Econoline E250","year":1993,"vin":"WVWAA7AH7AV977669"},
{"id":132,"car_make":"Eagle","car_model":"Summit","year":1994,"vin":"WP0AA2A81CU540116"},
{"id":133,"car_make":"Lincoln","car_model":"Zephyr","year":2006,"vin":"JN8AF5MR8DT800613"},
{"id":134,"car_make":"Volkswagen","car_model":"GTI","year":2009,"vin":"KNAGM4A76B5001405"},
{"id":135,"car_make":"Oldsmobile","car_model":"88","year":1995,"vin":"JM1NC2JF5E0074064"},
{"id":136,"car_make":"Volvo","car_model":"S80","year":1999,"vin":"JH4DC44651S583748"},
{"id":137,"car_make":"Rolls-Royce","car_model":"Phantom","year":2008,"vin":"JM1NC2LF4D0762410"},
{"id":138,"car_make":"Chevrolet","car_model":"Caprice","year":1992,"vin":"3C63D3ML7CG390187"},
{"id":139,"car_make":"Chevrolet","car_model":"Cavalier","year":2001,"vin":"JH4KA96674C225623"},
{"id":140,"car_make":"Mercury","car_model":"Grand Marquis","year":1989,"vin":"3VW517AT4FM436499"},
{"id":141,"car_make":"Chevrolet","car_model":"Silverado 2500","year":2010,"vin":"1G6YX36D985314628"},
{"id":142,"car_make":"Honda","car_model":"CR-X","year":1985,"vin":"1FTEW1E81AF244177"},
{"id":143,"car_make":"Mitsubishi","car_model":"Pajero","year":1988,"vin":"SAJWA8JH6EM617351"},
{"id":144,"car_make":"Smart","car_model":"Fortwo","year":2008,"vin":"JN8AE2KP0D9858120"},
{"id":145,"car_make":"Mitsubishi","car_model":"Truck","year":1991,"vin":"1B3AZ6JZ8AV579271"},
{"id":146,"car_make":"BMW","car_model":"8 Series","year":1992,"vin":"JTHBK1GG7F2214698"},
{"id":147,"car_make":"Mazda","car_model":"Miata MX-5","year":2004,"vin":"1G6DC1E30C0568998"},
{"id":148,"car_make":"Mitsubishi","car_model":"Mirage","year":1990,"vin":"WAUDK78T88A175943"},
{"id":149,"car_make":"Ford","car_model":"Escape","year":2008,"vin":"WAUHF98P07A854754"},
{"id":150,"car_make":"Porsche","car_model":"Boxster","year":2012,"vin":"1FTMF1E81AK668624"},
{"id":151,"car_make":"GMC","car_model":"Suburban 1500","year":1999,"vin":"WAUGFBFC1DN183165"},
{"id":152,"car_make":"Toyota","car_model":"Solara","year":2001,"vin":"WAUBH78E98A264993"},
{"id":153,"car_make":"Lexus","car_model":"IS","year":2004,"vin":"WAUHF78P08A774294"},
{"id":154,"car_make":"Isuzu","car_model":"Hombre Space","year":1998,"vin":"WAUPL58E05A015762"},
{"id":155,"car_make":"Lamborghini","car_model":"Countach","year":1988,"vin":"1D4SD6GT0BC266896"},
{"id":156,"car_make":"BMW","car_model":"7 Series","year":1999,"vin":"WDBWK5EA9BF539654"},
{"id":157,"car_make":"Toyota","car_model":"Land Cruiser","year":2001,"vin":"2G61L5S30F9169906"},
{"id":158,"car_make":"Volvo","car_model":"850","year":1996,"vin":"WAU2MAFC3EN981906"},
{"id":159,"car_make":"Hyundai","car_model":"Elantra","year":2012,"vin":"WBAVA33568K389414"},
{"id":160,"car_make":"Infiniti","car_model":"FX","year":2010,"vin":"5N1AA0NE9FN179684"},
{"id":161,"car_make":"GMC","car_model":"Savana 3500","year":2010,"vin":"WAUHFAFL1AA187167"},
{"id":162,"car_make":"Chrysler","car_model":"Town & Country","year":1992,"vin":"1N6AF0LY0EN182763"},
{"id":163,"car_make":"Acura","car_model":"TL","year":1996,"vin":"WAUDH94F97N611037"},
{"id":164,"car_make":"Ford","car_model":"Ranger","year":2002,"vin":"2C3CDXEJXFH904765"},
{"id":165,"car_make":"Jeep","car_model":"Grand Cherokee","year":2011,"vin":"KM8NU4CC4AU619682"},
{"id":166,"car_make":"Nissan","car_model":"Leaf","year":2012,"vin":"WAUDF98E65A156174"},
{"id":167,"car_make":"Oldsmobile","car_model":"Ciera","year":1993,"vin":"WVWED7AJXAW013864"},
{"id":168,"car_make":"Mitsubishi","car_model":"Truck","year":1987,"vin":"WVWAB7AJ2DW172371"},
{"id":169,"car_make":"Chevrolet","car_model":"Corvette","year":1998,"vin":"19UUA9F29BA691135"},
{"id":170,"car_make":"Hyundai","car_model":"Accent","year":2008,"vin":"WBALZ3C57CD076787"},
{"id":171,"car_make":"Saturn","car_model":"Sky","year":2007,"vin":"JTHBB1BA2B2491319"},
{"id":172,"car_make":"Ford","car_model":"E250","year":1984,"vin":"1GYS3EEJ8BR971190"},
{"id":173,"car_make":"Dodge","car_model":"Ram 2500 Club","year":1999,"vin":"KMHGH4JH1DU131256"},
{"id":174,"car_make":"Dodge","car_model":"Grand Caravan","year":2000,"vin":"3N1CN7APXFL926326"},
{"id":175,"car_make":"Nissan","car_model":"300ZX","year":1992,"vin":"1G6DK67V290571120"},
{"id":176,"car_make":"Audi","car_model":"Cabriolet","year":1997,"vin":"1D4RD2GG9BC598958"},
{"id":177,"car_make":"Subaru","car_model":"Leone","year":1985,"vin":"2LMDJ6JK2DB030333"},
{"id":178,"car_make":"Eagle","car_model":"Vision","year":1997,"vin":"2B3CA7CW7AH164637"},
{"id":179,"car_make":"Volkswagen","car_model":"Corrado","year":1991,"vin":"WVGEF9BP8DD201979"},
{"id":180,"car_make":"Kia","car_model":"Sportage","year":2000,"vin":"JTHBE1KS2A0107999"},
{"id":181,"car_make":"Chrysler","car_model":"Aspen","year":2008,"vin":"WUARL48H26K072253"},
{"id":182,"car_make":"BMW","car_model":"M5","year":2009,"vin":"3LN6L2G99DR607016"},
{"id":183,"car_make":"Dodge","car_model":"Ram Van 1500","year":1997,"vin":"1FTWF3C59AE552311"},
{"id":184,"car_make":"Mazda","car_model":"626","year":2002,"vin":"WA1WYBFE3AD576199"},
{"id":185,"car_make":"GMC","car_model":"1500","year":1995,"vin":"1G4GA5GR8FF394216"},
{"id":186,"car_make":"Mercury","car_model":"Sable","year":1999,"vin":"WAUDG78E86A764152"},
{"id":187,"car_make":"Mitsubishi","car_model":"Pajero","year":1988,"vin":"WA1CGAFE9ED479515"},
{"id":188,"car_make":"Dodge","car_model":"Avenger","year":2010,"vin":"2LMHJ5FK7FB372058"},
{"id":189,"car_make":"Chevrolet","car_model":"Caprice","year":1992,"vin":"WBAEK13436C055437"},
{"id":190,"car_make":"Plymouth","car_model":"Acclaim","year":1994,"vin":"1FAHP3EN5BW935055"},
{"id":191,"car_make":"Lexus","car_model":"IS","year":2008,"vin":"SALGS2TF8FA453900"},
{"id":192,"car_make":"Acura","car_model":"RL","year":2001,"vin":"1YVHZ8BH1A5286384"},
{"id":193,"car_make":"Jaguar","car_model":"XJ Series","year":2003,"vin":"5TDBCRFH5FS216210"},
{"id":194,"car_make":"Ford","car_model":"Mustang","year":1988,"vin":"WDDHF0EB3EB245906"},
{"id":195,"car_make":"Dodge","car_model":"Shadow","year":1993,"vin":"1FTEX1CM1DF333488"},
{"id":196,"car_make":"Mercedes-Benz","car_model":"S-Class","year":2004,"vin":"1VWAP7A34EC389441"},
{"id":197,"car_make":"Mazda","car_model":"MX-5","year":1993,"vin":"1N4AB7AP7DN882110"},
{"id":198,"car_make":"Volkswagen","car_model":"New Beetle","year":2000,"vin":"1FMCU0C78BK582116"},
{"id":199,"car_make":"Ford","car_model":"Torino","year":1970,"vin":"WAUFGAFC4FN675694"},
{"id":200,"car_make":"Lincoln","car_model":"MKZ","year":2010,"vin":"WP0AB2A80FK970524"},
{"id":201,"car_make":"Oldsmobile","car_model":"Cutlass Supreme","year":1997,"vin":"WBSDE93411B287501"},
{"id":202,"car_make":"Geo","car_model":"Tracker","year":1992,"vin":"1G6AH5S39F0729420"},
{"id":203,"car_make":"Hyundai","car_model":"Accent","year":2006,"vin":"WBAVC935X7K144305"},
{"id":204,"car_make":"GMC","car_model":"Suburban 1500","year":1993,"vin":"WAUEF78E27A926446"},
{"id":205,"car_make":"Honda","car_model":"Odyssey","year":2011,"vin":"JH4CU2F4XDC536576"},
{"id":206,"car_make":"Nissan","car_model":"350Z","year":2007,"vin":"JTDBT4K35A1277060"},
{"id":207,"car_make":"Chevrolet","car_model":"Suburban","year":2006,"vin":"4T1BK3DB6CU276529"},
{"id":208,"car_make":"Subaru","car_model":"Forester","year":2008,"vin":"WAUKH94F16N766185"},
{"id":209,"car_make":"Suzuki","car_model":"Samurai","year":1993,"vin":"JTJHY7AX1F4642970"},
{"id":210,"car_make":"GMC","car_model":"Yukon XL","year":2006,"vin":"5N1AA0NC0DN413562"},
{"id":211,"car_make":"Porsche","car_model":"Boxster","year":2001,"vin":"KL4CJGSB2EB259404"},
{"id":212,"car_make":"Dodge","car_model":"Ram 1500","year":2003,"vin":"5GALRCED2AJ506829"},
{"id":213,"car_make":"Kia","car_model":"Rio","year":2004,"vin":"1GD02ZCG5DZ051532"},
{"id":214,"car_make":"Lincoln","car_model":"Town Car","year":1997,"vin":"SCBDR33W58C714518"},
{"id":215,"car_make":"Audi","car_model":"Q7","year":2010,"vin":"1N6AA0EK4FN774658"},
{"id":216,"car_make":"Mazda","car_model":"626","year":1991,"vin":"1FTEX1C86AF838893"},
{"id":217,"car_make":"Honda","car_model":"Odyssey","year":1995,"vin":"2G61R5S31E9944274"},
{"id":218,"car_make":"Toyota","car_model":"Avalon","year":2005,"vin":"1G4HK5ES7BU304020"},
{"id":219,"car_make":"Mitsubishi","car_model":"Challenger","year":1998,"vin":"1GYS4DEF8CR418267"},
{"id":220,"car_make":"GMC","car_model":"Safari","year":2002,"vin":"WAUKF98E98A957774"},
{"id":221,"car_make":"GMC","car_model":"Savana 1500","year":2004,"vin":"2G4GU5GC2B9574345"},
{"id":222,"car_make":"Mercury","car_model":"Mariner","year":2005,"vin":"3GYFNCE39CS045185"},
{"id":223,"car_make":"Pontiac","car_model":"Daewoo Kalos","year":2006,"vin":"SCBCU7ZA8BC215801"},
{"id":224,"car_make":"Dodge","car_model":"Grand Caravan","year":1995,"vin":"SCFAD01A55G888356"},
{"id":225,"car_make":"Mercedes-Benz","car_model":"CLK-Class","year":2005,"vin":"1GYS3CEF2ER776318"},
{"id":226,"car_make":"Buick","car_model":"Century","year":1984,"vin":"SCFFDEDN7CG668019"},
{"id":227,"car_make":"GMC","car_model":"Yukon","year":2011,"vin":"1FTEW1CWXAF878749"},
{"id":228,"car_make":"Porsche","car_model":"944","year":1990,"vin":"WAUJC58E65A749926"},
{"id":229,"car_make":"Chrysler","car_model":"Pacifica","year":2007,"vin":"WBA3B1C5XEK168533"},
{"id":230,"car_make":"Dodge","car_model":"Ram 50","year":1992,"vin":"137ZA90351E711221"},
{"id":231,"car_make":"Chevrolet","car_model":"Astro","year":1997,"vin":"JH4CU2E68AC686474"},
{"id":232,"car_make":"Dodge","car_model":"Ram 1500 Club","year":1999,"vin":"SAJWA4HA6EM694495"},
{"id":233,"car_make":"Honda","car_model":"S2000","year":2001,"vin":"5NPEB4AC4BH423332"},
{"id":234,"car_make":"Jaguar","car_model":"X-Type","year":2004,"vin":"WVWAB7AJ9DW958751"},
{"id":235,"car_make":"Lincoln","car_model":"Continental","year":1997,"vin":"1N6AD0CU5EN702247"},
{"id":236,"car_make":"GMC","car_model":"Jimmy","year":2000,"vin":"JTDKDTB30C1852918"},
{"id":237,"car_make":"Dodge","car_model":"Stratus","year":1997,"vin":"WA1DGBFE8CD455715"},
{"id":238,"car_make":"Kia","car_model":"Forte","year":2010,"vin":"WBAFR9C50DC449353"},
{"id":239,"car_make":"Ford","car_model":"F250","year":1997,"vin":"WBAHL03526D062581"},
{"id":240,"car_make":"Land Rover","car_model":"Freelander","year":2010,"vin":"JN8AE2KP1F9403571"},
{"id":241,"car_make":"GMC","car_model":"Vandura 2500","year":1994,"vin":"WVWAA7AJ4CW710196"},
{"id":242,"car_make":"Subaru","car_model":"Impreza","year":2002,"vin":"WDDGF4HB7DR936957"},
{"id":243,"car_make":"Ford","car_model":"Focus","year":2011,"vin":"4JGBF2FBXAA891689"},
{"id":244,"car_make":"Volkswagen","car_model":"Rabbit","year":2007,"vin":"1G6AJ1R32F0127557"},
{"id":245,"car_make":"Toyota","car_model":"FJ Cruiser","year":2010,"vin":"2C3CDXEJ7DH747533"},
{"id":246,"car_make":"Cadillac","car_model":"Seville","year":1993,"vin":"1HGCR6F31EA655598"},
{"id":247,"car_make":"Toyota","car_model":"Sienna","year":1998,"vin":"1FTNS2EW4AD188960"},
{"id":248,"car_make":"Hyundai","car_model":"Azera","year":2010,"vin":"1G6DN8EV4A0754450"},
{"id":249,"car_make":"Lexus","car_model":"IS-F","year":2008,"vin":"SCBBB7ZH8FC661614"},
{"id":250,"car_make":"Toyota","car_model":"Celica","year":2004,"vin":"WA1EV94L08D757110"},
{"id":251,"car_make":"GMC","car_model":"Yukon XL 1500","year":2011,"vin":"WBAKB4C58CC417321"},
{"id":252,"car_make":"Mercedes-Benz","car_model":"W201","year":1988,"vin":"WAUKF78E78A960662"},
{"id":253,"car_make":"Volvo","car_model":"C30","year":2012,"vin":"3D73Y4HL4AG726958"},
{"id":254,"car_make":"Oldsmobile","car_model":"Silhouette","year":1995,"vin":"1C4RDJAGXFC004061"},
{"id":255,"car_make":"Saab","car_model":"9-5","year":2009,"vin":"SALVP2BG6FH911217"},
{"id":256,"car_make":"Dodge","car_model":"Ram 1500 Club","year":1999,"vin":"SCFAD22313K539054"},
{"id":257,"car_make":"Ford","car_model":"F150","year":1995,"vin":"2HKRM3H54DH052995"},
{"id":258,"car_make":"Toyota","car_model":"MR2","year":2001,"vin":"JH4NA12664T983408"},
{"id":259,"car_make":"Ford","car_model":"F-Series Super Duty","year":2009,"vin":"5TFBW5F14DX874868"},
{"id":260,"car_make":"Isuzu","car_model":"i-370","year":2008,"vin":"3GYFNAE38CS420701"},
{"id":261,"car_make":"Jeep","car_model":"Compass","year":2007,"vin":"WDDUG7JB4FA743257"},
{"id":262,"car_make":"Mercedes-Benz","car_model":"600SEC","year":1993,"vin":"2V4RW3DG6BR620252"},
{"id":263,"car_make":"Chevrolet","car_model":"Sportvan G30","year":1993,"vin":"1NXBU4EE2AZ036416"},
{"id":264,"car_make":"Chevrolet","car_model":"Corsica","year":1996,"vin":"WBA3C1C5XCF564271"},
{"id":265,"car_make":"Ford","car_model":"Fairlane","year":1967,"vin":"WAUKF78E95A021170"},
{"id":266,"car_make":"Kia","car_model":"Sorento","year":2006,"vin":"KL4CJHSB3FB307905"},
{"id":267,"car_make":"Mercedes-Benz","car_model":"SLK-Class","year":2006,"vin":"2B3CA8CT2AH415009"},
{"id":268,"car_make":"Pontiac","car_model":"Grand Am","year":2004,"vin":"1N4AL2EP3DC935746"},
{"id":269,"car_make":"Lexus","car_model":"LS","year":1997,"vin":"WVGEF9BP0FD676366"},
{"id":270,"car_make":"Volvo","car_model":"V70","year":2010,"vin":"WBA5A7C56FD605335"},
{"id":271,"car_make":"Jeep","car_model":"Grand Cherokee","year":2012,"vin":"JN8AZ1MU4DW906169"},
{"id":272,"car_make":"Fiat","car_model":"500","year":2012,"vin":"3D7JB1EK4BG313412"},
{"id":273,"car_make":"BMW","car_model":"7 Series","year":2009,"vin":"1G6DE5E59C0157277"},
{"id":274,"car_make":"Mercedes-Benz","car_model":"G-Class","year":2007,"vin":"SCBLC31E72C818166"},
{"id":275,"car_make":"Mitsubishi","car_model":"Galant","year":1990,"vin":"1C4RDJEGXEC127030"},
{"id":276,"car_make":"BMW","car_model":"X5","year":2013,"vin":"WAUHF78P06A988912"},
{"id":277,"car_make":"Chrysler","car_model":"Town & Country","year":1998,"vin":"5UXFE43588L805442"},
{"id":278,"car_make":"Audi","car_model":"TT","year":2003,"vin":"3VW517AT2FM978846"},
{"id":279,"car_make":"Dodge","car_model":"Shadow","year":1993,"vin":"JTDJTUD36ED918083"},
{"id":280,"car_make":"Volkswagen","car_model":"Passat","year":2010,"vin":"1C4SDHCTXFC829103"},
{"id":281,"car_make":"Mitsubishi","car_model":"Eclipse","year":1992,"vin":"WP0AA2A98ES322889"},
{"id":282,"car_make":"Ford","car_model":"F-Series","year":1996,"vin":"5N1AA0NC5EN828376"},
{"id":283,"car_make":"Mercedes-Benz","car_model":"M-Class","year":2001,"vin":"WDCGG0EB5EG682547"},
{"id":284,"car_make":"Mitsubishi","car_model":"Mirage","year":2001,"vin":"WBA3A9G56FN097827"},
{"id":285,"car_make":"Chevrolet","car_model":"Express 2500","year":2002,"vin":"WBAPH53529A165337"},
{"id":286,"car_make":"Infiniti","car_model":"QX","year":2006,"vin":"WAUML44EX6N933614"},
{"id":287,"car_make":"Chevrolet","car_model":"TrailBlazer","year":2008,"vin":"JH4KB16667C136077"},
{"id":288,"car_make":"Chevrolet","car_model":"Tahoe","year":2003,"vin":"SALAG2D47AA517549"},
{"id":289,"car_make":"GMC","car_model":"Vandura 2500","year":1994,"vin":"1G6DS1E38D0628742"},
{"id":290,"car_make":"Nissan","car_model":"Quest","year":2008,"vin":"1C4RDJDG2FC618744"},
{"id":291,"car_make":"Mitsubishi","car_model":"Mirage","year":1992,"vin":"SALFP2BN8BH423853"},
{"id":292,"car_make":"GMC","car_model":"Suburban 1500","year":1995,"vin":"WDDGF5EB6BR111970"},
{"id":293,"car_make":"Cadillac","car_model":"Escalade ESV","year":2010,"vin":"SCFAB22352K300885"},
{"id":294,"car_make":"Lexus","car_model":"RX","year":2010,"vin":"5N1AN0NU8CN236206"},
{"id":295,"car_make":"Ford","car_model":"F250","year":2007,"vin":"SCFFDECN3CG281338"},
{"id":296,"car_make":"Ford","car_model":"F-Series","year":2011,"vin":"19UUA66237A371685"},
{"id":297,"car_make":"Isuzu","car_model":"VehiCROSS","year":1999,"vin":"WDDLJ6HB3FA932964"},
{"id":298,"car_make":"Ford","car_model":"Bronco","year":1992,"vin":"2T1BU4EE0CC135725"},
{"id":299,"car_make":"Lotus","car_model":"Esprit","year":1990,"vin":"1GD11ZCGXCF694868"},
{"id":300,"car_make":"GMC","car_model":"Sierra 1500","year":2012,"vin":"JH4DC54855S829629"},
{"id":301,"car_make":"Volkswagen","car_model":"Cabriolet","year":1990,"vin":"4T1BD1FK3EU728824"},
{"id":302,"car_make":"Chevrolet","car_model":"Corvette","year":1997,"vin":"JH4CU2E60AC419233"},
{"id":303,"car_make":"Mitsubishi","car_model":"Expo","year":1992,"vin":"WDDGF4HB9DR356688"},
{"id":304,"car_make":"Lexus","car_model":"LS","year":1999,"vin":"19UUA86279A670613"},
{"id":305,"car_make":"Mitsubishi","car_model":"Endeavor","year":2008,"vin":"WAUMR44E46N144082"},
{"id":306,"car_make":"Ford","car_model":"F250","year":1997,"vin":"1N6BF0KL4FN151723"},
{"id":307,"car_make":"Hyundai","car_model":"Sonata","year":1994,"vin":"4T1BD1FK9EU353845"},
{"id":308,"car_make":"Land Rover","car_model":"Range Rover","year":2002,"vin":"1FMJK1G57DE380798"},
{"id":309,"car_make":"Chevrolet","car_model":"Corvair","year":1960,"vin":"WBAKG7C50CE070171"},
{"id":310,"car_make":"Ford","car_model":"Bronco","year":1991,"vin":"1G6KD57Y78U595751"},
{"id":311,"car_make":"Volkswagen","car_model":"Golf III","year":1995,"vin":"1FTEW1CMXEK378201"},
{"id":312,"car_make":"Pontiac","car_model":"Trans Sport","year":1991,"vin":"YV1902FH1B2576830"},
{"id":313,"car_make":"GMC","car_model":"Sonoma Club Coupe","year":1998,"vin":"5FRYD4H65GB599690"},
{"id":314,"car_make":"Toyota","car_model":"Land Cruiser","year":1992,"vin":"3FA6P0D93DR765049"},
{"id":315,"car_make":"Ford","car_model":"Mustang","year":1968,"vin":"WAUHFAFL4BA477162"},
{"id":316,"car_make":"Dodge","car_model":"Charger","year":1970,"vin":"WBAKE3C55CE901310"},
{"id":317,"car_make":"Chevrolet","car_model":"Corvette","year":1975,"vin":"2T2BK1BA2FC822520"},
{"id":318,"car_make":"Nissan","car_model":"Altima","year":2009,"vin":"WVWAB7AJ0CW890502"},
{"id":319,"car_make":"Merkur","car_model":"XR4Ti","year":1985,"vin":"JN8AZ2KR5AT199441"},
{"id":320,"car_make":"Chevrolet","car_model":"Corvette","year":1955,"vin":"SCFAB423X1K795742"},
{"id":321,"car_make":"Lincoln","car_model":"LS","year":2001,"vin":"1FTEX1C84AK587833"},
{"id":322,"car_make":"Lexus","car_model":"IS F","year":2009,"vin":"3C63DRLL3CG085421"},
{"id":323,"car_make":"Rolls-Royce","car_model":"Phantom","year":2010,"vin":"2C4RDGDG1CR456949"},
{"id":324,"car_make":"Volkswagen","car_model":"GTI","year":1987,"vin":"WBAKE3C56CE198171"},
{"id":325,"car_make":"GMC","car_model":"Sierra 1500","year":2010,"vin":"WBSBR93401E147823"},
{"id":326,"car_make":"Chevrolet","car_model":"Monte Carlo","year":1996,"vin":"WAUFGBFB9AN754137"},
{"id":327,"car_make":"Plymouth","car_model":"Colt Vista","year":1994,"vin":"1FTEX1CM5CF318572"},
{"id":328,"car_make":"Audi","car_model":"TT","year":2000,"vin":"1FTEX1C85AF667862"},
{"id":329,"car_make":"Chrysler","car_model":"New Yorker","year":1996,"vin":"SALVP2BG2FH465728"},
{"id":330,"car_make":"BMW","car_model":"X6 M","year":2012,"vin":"3D73Y3CL8AG337502"},
{"id":331,"car_make":"Cadillac","car_model":"Seville","year":2002,"vin":"WBAUN7C51CV984962"},
{"id":332,"car_make":"GMC","car_model":"Savana","year":2006,"vin":"1D7RV1CT0AS636885"},
{"id":333,"car_make":"Dodge","car_model":"Charger","year":2006,"vin":"3GYFNCE33CS242210"},
{"id":334,"car_make":"Nissan","car_model":"Sentra","year":2002,"vin":"5N1AN0NWXDN331479"},
{"id":335,"car_make":"Pontiac","car_model":"Bonneville","year":1985,"vin":"1G6DW677570318960"},
{"id":336,"car_make":"Chevrolet","car_model":"Cavalier","year":2000,"vin":"JM3ER2A51C0665860"},
{"id":337,"car_make":"Dodge","car_model":"Dakota","year":1998,"vin":"WA1LGAFE3CD720384"},
{"id":338,"car_make":"Audi","car_model":"TT","year":2006,"vin":"WAULT58E75A975160"},
{"id":339,"car_make":"Lexus","car_model":"GX","year":2010,"vin":"WAULT68E35A068881"},
{"id":340,"car_make":"Toyota","car_model":"Prius","year":2005,"vin":"SAJWA4DC4DM422646"},
{"id":341,"car_make":"Volkswagen","car_model":"Golf","year":2002,"vin":"WAUEFAFL2FN456473"},
{"id":342,"car_make":"Ford","car_model":"E-Series","year":2004,"vin":"1G6AJ1R33F0987418"},
{"id":343,"car_make":"Ford","car_model":"F150","year":1996,"vin":"2C3CDZBT0FH803266"},
{"id":344,"car_make":"Dodge","car_model":"Durango","year":2007,"vin":"5N1AN0NU9AC478088"},
{"id":345,"car_make":"Mitsubishi","car_model":"GTO","year":1996,"vin":"WAUBNAFB0BN862548"},
{"id":346,"car_make":"Lexus","car_model":"IS F","year":2009,"vin":"JN8AZ2KR6BT039330"},
{"id":347,"car_make":"Volkswagen","car_model":"Touareg","year":2005,"vin":"WA1YD54B75N000470"},
{"id":348,"car_make":"Lexus","car_model":"SC","year":2003,"vin":"KM8JT3AB3BU635721"},
{"id":349,"car_make":"Mitsubishi","car_model":"Tredia","year":1984,"vin":"5XYKT3A10BG983249"},
{"id":350,"car_make":"Buick","car_model":"LeSabre","year":1988,"vin":"WAUAF48H79K797026"},
{"id":351,"car_make":"Cadillac","car_model":"Escalade EXT","year":2011,"vin":"1G6AH5RX2F0722771"},
{"id":352,"car_make":"Volvo","car_model":"S40","year":2003,"vin":"JTHBB1BA6B2197440"},
{"id":353,"car_make":"Toyota","car_model":"Sienna","year":2011,"vin":"2D4RN7DG7BR953180"},
{"id":354,"car_make":"Mitsubishi","car_model":"Endeavor","year":2011,"vin":"JN8AE2KP1F9411539"},
{"id":355,"car_make":"GMC","car_model":"Sonoma Club Coupe","year":1993,"vin":"3N1CN7AP1EL467525"},
{"id":356,"car_make":"Lexus","car_model":"LS","year":1992,"vin":"WAUAH74F36N211089"},
{"id":357,"car_make":"Mitsubishi","car_model":"Lancer","year":2010,"vin":"JN1CV6AR3FM602099"},
{"id":358,"car_make":"Lexus","car_model":"IS","year":2012,"vin":"KNADH4A32A6561239"},
{"id":359,"car_make":"Buick","car_model":"Riviera","year":1988,"vin":"5J8TB3H76GL324560"},
{"id":360,"car_make":"Mercedes-Benz","car_model":"CLS-Class","year":2006,"vin":"2G61R5S34E9609865"},
{"id":361,"car_make":"Chevrolet","car_model":"2500","year":1997,"vin":"WBALW7C53ED818847"},
{"id":362,"car_make":"Toyota","car_model":"RAV4","year":2010,"vin":"4A37L3ET4AE961633"},
{"id":363,"car_make":"Scion","car_model":"xA","year":2005,"vin":"WDBWK5JAXBF687785"},
{"id":364,"car_make":"GMC","car_model":"Savana 3500","year":1999,"vin":"JM1BL1K55B1167238"},
{"id":365,"car_make":"Honda","car_model":"Insight","year":2004,"vin":"WA1BV94L68D824912"},
{"id":366,"car_make":"Nissan","car_model":"JUKE","year":2011,"vin":"19UUA75597A215605"},
{"id":367,"car_make":"Mazda","car_model":"Millenia","year":1999,"vin":"2C3CCAKG0FH453435"},
{"id":368,"car_make":"Chevrolet","car_model":"Tahoe","year":1999,"vin":"WBAEH13527C359920"},
{"id":369,"car_make":"Volvo","car_model":"C70","year":2003,"vin":"5FPYK1F2XCB920503"},
{"id":370,"car_make":"BMW","car_model":"M6","year":2009,"vin":"1G6DJ1E34C0788361"},
{"id":371,"car_make":"Land Rover","car_model":"Discovery","year":2006,"vin":"TRUSC28N341188613"},
{"id":372,"car_make":"Mazda","car_model":"Protege","year":1993,"vin":"3FADP4AJ0BM109057"},
{"id":373,"car_make":"Mercedes-Benz","car_model":"C-Class","year":2002,"vin":"1FTEX1CM1BK918978"},
{"id":374,"car_make":"Ford","car_model":"Econoline E350","year":1993,"vin":"1G6KD54Y42U750722"},
{"id":375,"car_make":"Mercedes-Benz","car_model":"C-Class","year":2012,"vin":"JTDKN3DU6F0344272"},
{"id":376,"car_make":"Volvo","car_model":"S40","year":2003,"vin":"JM1DE1KY0D0643871"},
{"id":377,"car_make":"Ford","car_model":"F150","year":2011,"vin":"2C3CCAKG5EH680702"},
{"id":378,"car_make":"Nissan","car_model":"Frontier","year":2003,"vin":"1FTWF3D51AE990027"},
{"id":379,"car_make":"Ford","car_model":"Taurus","year":2004,"vin":"1D4RD4GG8BC957079"},
{"id":380,"car_make":"Ford","car_model":"Escape","year":2004,"vin":"WBASP2C53BC641651"},
{"id":381,"car_make":"Dodge","car_model":"D350","year":1992,"vin":"VNKKTUD30FA972851"},
{"id":382,"car_make":"Chrysler","car_model":"Crossfire","year":2006,"vin":"1D7RV1GP2BS347909"},
{"id":383,"car_make":"Nissan","car_model":"Titan","year":2012,"vin":"5J8TB3H32EL214616"},
{"id":384,"car_make":"Eagle","car_model":"Vision","year":1994,"vin":"2G4GR5EC7B9891557"},
{"id":385,"car_make":"Ford","car_model":"Focus","year":2002,"vin":"3D7TP2CT5AG229805"},
{"id":386,"car_make":"Chevrolet","car_model":"Corsica","year":1993,"vin":"1N6AA0EC6DN301009"},
{"id":387,"car_make":"Audi","car_model":"100","year":1990,"vin":"WBAGN83544D993004"},
{"id":388,"car_make":"Kia","car_model":"Rondo","year":2009,"vin":"WA1LFAFP4FA260792"},
{"id":389,"car_make":"Honda","car_model":"Civic","year":2006,"vin":"WAUGFAFR3DA146432"},
{"id":390,"car_make":"Cadillac","car_model":"Escalade","year":2010,"vin":"KMHDB8AE2AU390092"},
{"id":391,"car_make":"Pontiac","car_model":"Firebird","year":1998,"vin":"WBAYM1C54FD729122"},
{"id":392,"car_make":"BMW","car_model":"X3","year":2010,"vin":"1G6AX5SX1F0759176"},
{"id":393,"car_make":"Toyota","car_model":"Prius c","year":2012,"vin":"WAUHFAFLXBA421131"},
{"id":394,"car_make":"Kia","car_model":"Sportage","year":2010,"vin":"JN1AZ4EHXAM971004"},
{"id":395,"car_make":"Volkswagen","car_model":"Type 2","year":1987,"vin":"WBAPM73589A712859"},
{"id":396,"car_make":"Hyundai","car_model":"Accent","year":2004,"vin":"JTJBC1BA3B2827085"},
{"id":397,"car_make":"Ford","car_model":"Aerostar","year":1988,"vin":"WA1YD54B12N901071"},
{"id":398,"car_make":"Jeep","car_model":"Wrangler","year":1995,"vin":"YV1672MC5BJ423847"},
{"id":399,"car_make":"Toyota","car_model":"Camry","year":2011,"vin":"WAU3FAFR3DA640160"},
{"id":400,"car_make":"Chevrolet","car_model":"Express 2500","year":2011,"vin":"JTEBU5JR8B5810422"},
{"id":401,"car_make":"Volkswagen","car_model":"Cabriolet","year":1997,"vin":"3C6TD4MT8CG057812"},
{"id":402,"car_make":"Honda","car_model":"Passport","year":2000,"vin":"JN1BV7AP0FM430730"},
{"id":403,"car_make":"Ford","car_model":"Ranger","year":1993,"vin":"TRUWC28N611701429"},
{"id":404,"car_make":"Pontiac","car_model":"Grand Prix","year":1964,"vin":"WAUVFAFRXDA083756"},
{"id":405,"car_make":"Chevrolet","car_model":"Impala SS","year":1995,"vin":"WA1AY94L29D670607"},
{"id":406,"car_make":"Geo","car_model":"Tracker","year":1996,"vin":"5J8TB3H35EL982641"},
{"id":407,"car_make":"Mitsubishi","car_model":"Montero","year":2003,"vin":"1G6AF5SX9E0957246"},
{"id":408,"car_make":"BMW","car_model":"530","year":2001,"vin":"3D7JB1EP2BG200909"},
{"id":409,"car_make":"GMC","car_model":"Jimmy","year":1993,"vin":"WAUVT58E42A651300"},
{"id":410,"car_make":"Jeep","car_model":"Compass","year":2008,"vin":"1FTMF1CW2AF412549"},
{"id":411,"car_make":"Buick","car_model":"Electra","year":1988,"vin":"1GKS1EEF8ER604550"},
{"id":412,"car_make":"BMW","car_model":"M Roadster","year":2007,"vin":"1D7RB1GK9AS103718"},
{"id":413,"car_make":"Mitsubishi","car_model":"Truck","year":1989,"vin":"WBABV134X6J432285"},
{"id":414,"car_make":"Toyota","car_model":"Land Cruiser","year":2005,"vin":"SAJWA8JH2EM447974"},
{"id":415,"car_make":"Honda","car_model":"S2000","year":2006,"vin":"WAULFAFRXAA031109"},
{"id":416,"car_make":"Hyundai","car_model":"Sonata","year":2003,"vin":"SCFFDAAM7DG433710"},
{"id":417,"car_make":"Porsche","car_model":"944","year":1988,"vin":"2C3CCADT2CH268650"},
{"id":418,"car_make":"Mercedes-Benz","car_model":"M-Class","year":2002,"vin":"5N1AN0NU7BC751711"},
{"id":419,"car_make":"Ford","car_model":"Lightning","year":1994,"vin":"2G4WE587561669044"},
{"id":420,"car_make":"Pontiac","car_model":"G6","year":2010,"vin":"WAU2MAFC0EN750817"},
{"id":421,"car_make":"GMC","car_model":"Acadia","year":2011,"vin":"WAUAG78EX6A315994"},
{"id":422,"car_make":"Dodge","car_model":"Dakota","year":1997,"vin":"WAUBVAFB9AN967569"},
{"id":423,"car_make":"Toyota","car_model":"T100 Xtra","year":1995,"vin":"1N4AL2APXCN353300"},
{"id":424,"car_make":"GMC","car_model":"Savana 2500","year":1999,"vin":"3VW117AU0FM570434"},
{"id":425,"car_make":"Ford","car_model":"Laser","year":1988,"vin":"JN1CV6AP4CM428523"},
{"id":426,"car_make":"Chevrolet","car_model":"Venture","year":1998,"vin":"2HNYB1H49CH042249"},
{"id":427,"car_make":"Pontiac","car_model":"Firebird","year":1968,"vin":"JTHBK1EG7C2206163"},
{"id":428,"car_make":"Mercedes-Benz","car_model":"CLK-Class","year":1999,"vin":"KMHCM3AC4AU114245"},
{"id":429,"car_make":"Suzuki","car_model":"Sidekick","year":1990,"vin":"19UUA75528A817845"},
{"id":430,"car_make":"Mazda","car_model":"MX-5","year":1996,"vin":"WAUDT94F55N284566"},
{"id":431,"car_make":"Volkswagen","car_model":"GTI","year":1985,"vin":"SCFAB22333K005768"},
{"id":432,"car_make":"Mitsubishi","car_model":"i-MiEV","year":2012,"vin":"WBAEH13597C750112"},
{"id":433,"car_make":"Volkswagen","car_model":"Routan","year":2012,"vin":"3GYFNBEY8BS104263"},
{"id":434,"car_make":"Toyota","car_model":"4Runner","year":1999,"vin":"1C3CC4FB1AN300921"},
{"id":435,"car_make":"Ford","car_model":"Econoline E250","year":1994,"vin":"WAUSF98EX8A021842"},
{"id":436,"car_make":"Bentley","car_model":"Continental Flying Spur","year":2011,"vin":"WAUXF78K89A098548"},
{"id":437,"car_make":"MINI","car_model":"Cooper","year":2009,"vin":"WP0CB2A80CS226541"},
{"id":438,"car_make":"Ford","car_model":"Focus","year":2002,"vin":"5FPYK1F54EB077797"},
{"id":439,"car_make":"Mitsubishi","car_model":"Truck","year":1986,"vin":"1FTMF1EW5AF947758"},
{"id":440,"car_make":"Suzuki","car_model":"Cultus","year":1985,"vin":"WAUFFAFL8FN380584"},
{"id":441,"car_make":"Mazda","car_model":"MPV","year":1998,"vin":"WBA3B1C58DF258237"},
{"id":442,"car_make":"Plymouth","car_model":"Grand Voyager","year":1992,"vin":"1FMCU0F73FU424188"},
{"id":443,"car_make":"Infiniti","car_model":"FX","year":2011,"vin":"WBADX1C55CJ496533"},
{"id":444,"car_make":"Toyota","car_model":"Echo","year":2005,"vin":"3C63D2EL8CG217562"},
{"id":445,"car_make":"Pontiac","car_model":"Grand Prix","year":1986,"vin":"1FTMF1CWXAK828694"},
{"id":446,"car_make":"Volkswagen","car_model":"Phaeton","year":2004,"vin":"1FTSW2A57AE596349"},
{"id":447,"car_make":"Volkswagen","car_model":"Jetta","year":1986,"vin":"1G4HC5EM7AU049947"},
{"id":448,"car_make":"Buick","car_model":"LeSabre","year":2002,"vin":"YV1672MS6B2708767"},
{"id":449,"car_make":"Toyota","car_model":"Tacoma Xtra","year":1995,"vin":"WBAUN1C5XBV601693"},
{"id":450,"car_make":"Chevrolet","car_model":"Camaro","year":2002,"vin":"JTHBL5EF5F1317154"},
{"id":451,"car_make":"Buick","car_model":"Regal","year":1995,"vin":"1G6AG1RX6F0770236"},
{"id":452,"car_make":"Hyundai","car_model":"XG350","year":2004,"vin":"3GYEK62NX6G170621"},
{"id":453,"car_make":"Honda","car_model":"Insight","year":2000,"vin":"JHMZE2H53ES367456"},
{"id":454,"car_make":"Porsche","car_model":"Cayenne","year":2009,"vin":"1N4AB7AP3DN323850"},
{"id":455,"car_make":"Acura","car_model":"Legend","year":1992,"vin":"WAUD2AFD3DN761557"},
{"id":456,"car_make":"Chevrolet","car_model":"Suburban 1500","year":2007,"vin":"2G4GS5EV2D9717338"},
{"id":457,"car_make":"Dodge","car_model":"Grand Caravan","year":1998,"vin":"1N4AB7AP9DN282771"},
{"id":458,"car_make":"Volkswagen","car_model":"Scirocco","year":1984,"vin":"WA1YD64B14N974367"},
{"id":459,"car_make":"Bentley","car_model":"Continental GT","year":2006,"vin":"WAUKG78E56A919568"},
{"id":460,"car_make":"Toyota","car_model":"Prius","year":2005,"vin":"3N1CN7AP0FL895605"},
{"id":461,"car_make":"Infiniti","car_model":"G37","year":2011,"vin":"19UUA65636A657586"},
{"id":462,"car_make":"Ford","car_model":"F-Series","year":1991,"vin":"1ZVBP8JS6C5305932"},
{"id":463,"car_make":"Hyundai","car_model":"Scoupe","year":1995,"vin":"1D4PT7GXXBW802981"},
{"id":464,"car_make":"Dodge","car_model":"Ram 3500","year":1994,"vin":"WAULT68E95A857567"},
{"id":465,"car_make":"Chevrolet","car_model":"Avalanche","year":2002,"vin":"SCFEBBBK2EG890933"},
{"id":466,"car_make":"Chevrolet","car_model":"Blazer","year":2001,"vin":"JN8AF5MR5ET358374"},
{"id":467,"car_make":"Mitsubishi","car_model":"Diamante","year":1997,"vin":"1GYS3FEJ7BR148787"},
{"id":468,"car_make":"GMC","car_model":"Jimmy","year":1998,"vin":"JTEBU5JR5F5991243"},
{"id":469,"car_make":"Lotus","car_model":"Elise","year":2005,"vin":"WAUXU64B13N452075"},
{"id":470,"car_make":"Ford","car_model":"Econoline E250","year":1995,"vin":"JN1CV6EK6CM513961"},
{"id":471,"car_make":"Saturn","car_model":"Sky","year":2007,"vin":"JH4DB755X1S403402"},
{"id":472,"car_make":"Ford","car_model":"E-Series","year":1990,"vin":"JH4DB76581S945614"},
{"id":473,"car_make":"Chevrolet","car_model":"Camaro","year":2002,"vin":"19VDE2E56EE503123"},
{"id":474,"car_make":"Chevrolet","car_model":"Silverado","year":2011,"vin":"WAUKH78EX6A309081"},
{"id":475,"car_make":"Pontiac","car_model":"Gemini","year":1986,"vin":"5N1AT2MLXEC014582"},
{"id":476,"car_make":"BMW","car_model":"M3","year":2004,"vin":"3D73Y4CL2AG111946"},
{"id":477,"car_make":"Ford","car_model":"Crown Victoria","year":2008,"vin":"SALWR2VFXFA564999"},
{"id":478,"car_make":"Saab","car_model":"9-5","year":2002,"vin":"5UXZV4C57BL664058"},
{"id":479,"car_make":"Mazda","car_model":"Mazda3","year":2009,"vin":"WBAKA8C59AC658473"},
{"id":480,"car_make":"Mitsubishi","car_model":"Mirage","year":1991,"vin":"WAUHF78P38A947290"},
{"id":481,"car_make":"Buick","car_model":"Regal","year":1992,"vin":"3C3CFFARXFT468006"},
{"id":482,"car_make":"Toyota","car_model":"Prius v","year":2012,"vin":"JTDKDTB38F1493757"},
{"id":483,"car_make":"Mitsubishi","car_model":"RVR","year":1992,"vin":"1C3CDFDH9ED680618"},
{"id":484,"car_make":"Ford","car_model":"Crown Victoria","year":2004,"vin":"JN8AF5MR6ET604204"},
{"id":485,"car_make":"Mitsubishi","car_model":"Montero Sport","year":1998,"vin":"3D7JB1ET8BG890274"},
{"id":486,"car_make":"Mercury","car_model":"Grand Marquis","year":2008,"vin":"JN1AV7AR4FM461427"},
{"id":487,"car_make":"Audi","car_model":"S6","year":2002,"vin":"1VWAH7A38DC476187"},
{"id":488,"car_make":"Bentley","car_model":"Continental Flying Spur","year":2010,"vin":"JN8AZ2NC4B9472391"},
{"id":489,"car_make":"Nissan","car_model":"350Z","year":2006,"vin":"WBAPH7C53AE078460"},
{"id":490,"car_make":"Audi","car_model":"90","year":1991,"vin":"SCFBF04B17G549728"},
{"id":491,"car_make":"GMC","car_model":"Savana 3500","year":2010,"vin":"JH4CL96958C714794"},
{"id":492,"car_make":"Subaru","car_model":"Legacy","year":2002,"vin":"1GYUCAEF7AR190012"},
{"id":493,"car_make":"Chevrolet","car_model":"Tahoe","year":2005,"vin":"WA1LGAFE7FD519172"},
{"id":494,"car_make":"Dodge","car_model":"Stratus","year":2001,"vin":"JM1DE1KY6D0539000"},
{"id":495,"car_make":"Dodge","car_model":"Viper","year":2003,"vin":"2G4WS52J051882544"},
{"id":496,"car_make":"Jeep","car_model":"Wrangler","year":2008,"vin":"5J6TF1H36DL803491"},
{"id":497,"car_make":"Lamborghini","car_model":"Gallardo","year":2010,"vin":"JM1NC2EF6A0833308"},
{"id":498,"car_make":"Ford","car_model":"F250","year":2003,"vin":"JN1BJ0HR9DM433603"},
{"id":499,"car_make":"Mitsubishi","car_model":"3000GT","year":1995,"vin":"137ZA843X1E969688"},
{"id":500,"car_make":"Aston Martin","car_model":"Vanquish S","year":2006,"vin":"YV126MFC3F1369545"},
{"id":501,"car_make":"Ford","car_model":"Econoline E250","year":1997,"vin":"WAUKH94F16N286387"},
{"id":502,"car_make":"Jeep","car_model":"Grand Cherokee","year":2003,"vin":"SCBBR53W36C646560"},
{"id":503,"car_make":"Lotus","car_model":"Esprit","year":1994,"vin":"WAUWFBFL6CA436269"},
{"id":504,"car_make":"Infiniti","car_model":"FX","year":2006,"vin":"1G6DH8E57C0657253"},
{"id":505,"car_make":"Mercedes-Benz","car_model":"CL-Class","year":2000,"vin":"JN1BY0AR2AM993349"},
{"id":506,"car_make":"Pontiac","car_model":"LeMans","year":1967,"vin":"WA1AV94LX7D434020"},
{"id":507,"car_make":"Nissan","car_model":"Sentra","year":1997,"vin":"1D4RD2GG6BC317943"},
{"id":508,"car_make":"Toyota","car_model":"Sienna","year":2012,"vin":"1G6DM5EGXA0298117"},
{"id":509,"car_make":"Buick","car_model":"Skyhawk","year":1989,"vin":"JH4NA21694T046883"},
{"id":510,"car_make":"Pontiac","car_model":"Vibe","year":2003,"vin":"WP1AA2A27CL993136"},
{"id":511,"car_make":"Mercury","car_model":"Villager","year":2000,"vin":"3GYFNFEY0BS184018"},
{"id":512,"car_make":"Lincoln","car_model":"Town Car","year":2010,"vin":"5UXFA13565L277230"},
{"id":513,"car_make":"Hyundai","car_model":"Sonata","year":1998,"vin":"3C3CFFAR5DT851509"},
{"id":514,"car_make":"Mercedes-Benz","car_model":"CL-Class","year":1998,"vin":"1G6DM8E30D0554638"},
{"id":515,"car_make":"BMW","car_model":"7 Series","year":1994,"vin":"1N6AF0KY5FN635794"},
{"id":516,"car_make":"BMW","car_model":"Z8","year":2000,"vin":"JM3KE2BE9D0030657"},
{"id":517,"car_make":"Maybach","car_model":"57","year":2005,"vin":"1N6AD0CU5AC366881"},
{"id":518,"car_make":"Jeep","car_model":"Wrangler","year":1998,"vin":"4T1BD1EB1DU349773"},
{"id":519,"car_make":"Audi","car_model":"A8","year":2008,"vin":"5N1AR2MM6EC058022"},
{"id":520,"car_make":"Isuzu","car_model":"Hombre","year":1999,"vin":"WA1BV94L57D891922"},
{"id":521,"car_make":"Kia","car_model":"Sedona","year":2009,"vin":"5NPDH4AE1FH679624"},
{"id":522,"car_make":"Lotus","car_model":"Elise","year":2007,"vin":"WAUMFAFR8EA125483"},
{"id":523,"car_make":"Mitsubishi","car_model":"Montero Sport","year":2003,"vin":"WAUVT68E94A562184"},
{"id":524,"car_make":"Mercedes-Benz","car_model":"SLK-Class","year":2001,"vin":"1B3AZ6EZ2AV489074"},
{"id":525,"car_make":"Ford","car_model":"E-Series","year":1989,"vin":"5TDBW5G12DS485568"},
{"id":526,"car_make":"Volkswagen","car_model":"Jetta","year":2010,"vin":"19UYA42401A053902"},
{"id":527,"car_make":"Toyota","car_model":"Corolla","year":2000,"vin":"WDDNG9FB5CA601844"},
{"id":528,"car_make":"Infiniti","car_model":"I","year":2004,"vin":"WAUJFAFH1CN826558"},
{"id":529,"car_make":"Nissan","car_model":"Maxima","year":1996,"vin":"1FTEX1E87AF141231"},
{"id":530,"car_make":"Eagle","car_model":"Premier","year":1992,"vin":"2C3CDXBG2EH535679"},
{"id":531,"car_make":"Porsche","car_model":"911","year":2013,"vin":"WAUPFAFM7BA619332"},
{"id":532,"car_make":"Infiniti","car_model":"G25","year":2011,"vin":"SALVP1BG4EH209423"},
{"id":533,"car_make":"Bentley","car_model":"Azure","year":2008,"vin":"JM3ER2A50B0130985"},
{"id":534,"car_make":"Saab","car_model":"9-3","year":2002,"vin":"1FTEX1EW7AF223555"},
{"id":535,"car_make":"Plymouth","car_model":"Voyager","year":1994,"vin":"JH4CL96836C777770"},
{"id":536,"car_make":"Kia","car_model":"Sedona","year":2004,"vin":"WBA6B2C51FG195983"},
{"id":537,"car_make":"Suzuki","car_model":"Grand Vitara","year":2002,"vin":"WAUVC68E44A831174"},
{"id":538,"car_make":"GMC","car_model":"Canyon","year":2006,"vin":"WAUWMAFC2FN573805"},
{"id":539,"car_make":"Chevrolet","car_model":"Monte Carlo","year":2004,"vin":"1C4SDJCT3DC332611"},
{"id":540,"car_make":"Chevrolet","car_model":"Silverado 1500","year":2007,"vin":"1N6AF0KX6EN210140"},
{"id":541,"car_make":"Saab","car_model":"9-3","year":2000,"vin":"WBAWB7C52AP694703"},
{"id":542,"car_make":"Hummer","car_model":"H1","year":2006,"vin":"2FMDK3JC8AB233395"},
{"id":543,"car_make":"Land Rover","car_model":"LR2","year":2012,"vin":"WAUWGAFC9EN888817"},
{"id":544,"car_make":"Ford","car_model":"E250","year":2004,"vin":"WAUUL98E27A131543"},
{"id":545,"car_make":"Oldsmobile","car_model":"Ciera","year":1993,"vin":"WUADUAFG3F7546553"},
{"id":546,"car_make":"Mitsubishi","car_model":"Mirage","year":1993,"vin":"JN1CV6AP1BM430406"},
{"id":547,"car_make":"Ford","car_model":"F-Series","year":1986,"vin":"JA32X2HU3EU494280"},
{"id":548,"car_make":"BMW","car_model":"1 Series","year":2009,"vin":"1G6YV36A395436463"},
{"id":549,"car_make":"Mazda","car_model":"Mazda3","year":2006,"vin":"JH4CU2E86EC835357"},
{"id":550,"car_make":"Honda","car_model":"Accord","year":1993,"vin":"3VW4A7AT0DM462686"},
{"id":551,"car_make":"Mercury","car_model":"Sable","year":1990,"vin":"4F2CY0C77AK469705"},
{"id":552,"car_make":"Ford","car_model":"ZX2","year":2001,"vin":"KMHTC6AD7DU381753"},
{"id":553,"car_make":"Honda","car_model":"S2000","year":2003,"vin":"1G6AJ5SX2D0525238"},
{"id":554,"car_make":"Volkswagen","car_model":"Eos","year":2010,"vin":"JN8AF5MR5BT215856"},
{"id":555,"car_make":"Hyundai","car_model":"Elantra","year":2004,"vin":"WBAPH7C5XBA781370"},
{"id":556,"car_make":"Mazda","car_model":"B-Series","year":2003,"vin":"3GTXKYEJ3AG339857"},
{"id":557,"car_make":"Subaru","car_model":"Impreza WRX","year":2010,"vin":"1GYFC53279R157779"},
{"id":558,"car_make":"Hyundai","car_model":"Accent","year":2001,"vin":"1FTFW1E85AF464622"},
{"id":559,"car_make":"Chevrolet","car_model":"Suburban 1500","year":1995,"vin":"1N6AF0LY7FN483421"},
{"id":560,"car_make":"Toyota","car_model":"Tundra","year":2007,"vin":"1FMJK1G50CE069888"},
{"id":561,"car_make":"Chrysler","car_model":"New Yorker","year":1995,"vin":"WA1CMAFPXFA320290"},
{"id":562,"car_make":"Hyundai","car_model":"Tiburon","year":1998,"vin":"WBAPK5C54BF701599"},
{"id":563,"car_make":"Lexus","car_model":"LS","year":2012,"vin":"WAUKH68D41A237563"},
{"id":564,"car_make":"Porsche","car_model":"928","year":1994,"vin":"ZFBCFADH1FZ355509"},
{"id":565,"car_make":"Chevrolet","car_model":"Express 2500","year":2012,"vin":"4T1BK3DB5CU823886"},
{"id":566,"car_make":"Chrysler","car_model":"LHS","year":1996,"vin":"1D7RW3BK4AS008099"},
{"id":567,"car_make":"Ford","car_model":"F150","year":1997,"vin":"WBA3K5C54EK141173"},
{"id":568,"car_make":"Buick","car_model":"Skylark","year":1995,"vin":"1G6DL8ED8B0348735"},
{"id":569,"car_make":"Dodge","car_model":"Durango","year":1999,"vin":"1G6DV5EP0E0565378"},
{"id":570,"car_make":"Buick","car_model":"Riviera","year":1979,"vin":"1FTMF1CW7AF018349"},
{"id":571,"car_make":"Hyundai","car_model":"Santa Fe","year":2002,"vin":"2T1BURHE9EC155628"},
{"id":572,"car_make":"Ford","car_model":"Expedition","year":2012,"vin":"1FT7W2A60EE465882"},
{"id":573,"car_make":"Porsche","car_model":"Cayenne","year":2008,"vin":"2V4RW3DG6BR762987"},
{"id":574,"car_make":"Audi","car_model":"V8","year":1994,"vin":"1D4SE6GTXBC766271"},
{"id":575,"car_make":"Ford","car_model":"Explorer Sport Trac","year":2005,"vin":"2C3CDXGJ8DH202079"},
{"id":576,"car_make":"Honda","car_model":"Ridgeline","year":2006,"vin":"3C6LD4BT3CG003269"},
{"id":577,"car_make":"Mercury","car_model":"Villager","year":2001,"vin":"JTHBB1BA4A2321252"},
{"id":578,"car_make":"Buick","car_model":"Riviera","year":1979,"vin":"KMHEC4A42EA839666"},
{"id":579,"car_make":"Kia","car_model":"Soul","year":2011,"vin":"2LMHJ5AT2FB484833"},
{"id":580,"car_make":"Mitsubishi","car_model":"Starion","year":1986,"vin":"SCFAD22353K197981"},
{"id":581,"car_make":"Mazda","car_model":"Miata MX-5","year":2011,"vin":"WAUHF98P69A540996"},
{"id":582,"car_make":"Lincoln","car_model":"MKZ","year":2009,"vin":"1C4RDJEG5EC866001"},
{"id":583,"car_make":"BMW","car_model":"330","year":2005,"vin":"1FMNE1BW6AD539384"},
{"id":584,"car_make":"Honda","car_model":"Prelude","year":1994,"vin":"1G6AG1RXXF0667918"},
{"id":585,"car_make":"Acura","car_model":"Integra","year":1999,"vin":"1VWAS7A31FC716510"},
{"id":586,"car_make":"Chevrolet","car_model":"3500","year":1998,"vin":"1FTEW1C87AF352001"},
{"id":587,"car_make":"Dodge","car_model":"D350 Club","year":1993,"vin":"5FRYD3H99GB129585"},
{"id":588,"car_make":"Ford","car_model":"Ranger","year":2000,"vin":"4T1BK1EB0EU707629"},
{"id":589,"car_make":"Chevrolet","car_model":"Corvette","year":1973,"vin":"3N1CN7AP8DL367050"},
{"id":590,"car_make":"Chevrolet","car_model":"Aveo","year":2004,"vin":"JM1NC2PF5E0136506"},
{"id":591,"car_make":"Infiniti","car_model":"J","year":1994,"vin":"1FTSX2B5XAE497794"},
{"id":592,"car_make":"Kia","car_model":"Spectra","year":2001,"vin":"WAUBF78E88A554700"},
{"id":593,"car_make":"Pontiac","car_model":"Bonneville","year":1985,"vin":"5NPDH4AE3EH596033"},
{"id":594,"car_make":"BMW","car_model":"525","year":2002,"vin":"4T1BK3DB1CU446120"},
{"id":595,"car_make":"Mitsubishi","car_model":"Mirage","year":1985,"vin":"WAUML54B82N501979"},
{"id":596,"car_make":"Volvo","car_model":"S40","year":2008,"vin":"WBAUU3C51BA616914"},
{"id":597,"car_make":"Mitsubishi","car_model":"Chariot","year":1993,"vin":"KNADM4A31C6080994"},
{"id":598,"car_make":"Toyota","car_model":"Celica","year":2001,"vin":"SCBZB25EX1C824334"},
{"id":599,"car_make":"Mercedes-Benz","car_model":"SLR McLaren","year":2005,"vin":"1GYFK26249R997659"},
{"id":600,"car_make":"Mazda","car_model":"Familia","year":1987,"vin":"WBA3B3G59FN487962"},
{"id":601,"car_make":"Lexus","car_model":"RX","year":2000,"vin":"5UXFA53502L384518"},
{"id":602,"car_make":"Honda","car_model":"Civic","year":2000,"vin":"1G6DP57VX80205304"},
{"id":603,"car_make":"Chevrolet","car_model":"Corvette","year":1989,"vin":"WBAPH7C54BE161297"},
{"id":604,"car_make":"Buick","car_model":"LaCrosse","year":2009,"vin":"WAULT54B53N476892"},
{"id":605,"car_make":"Mitsubishi","car_model":"Expo","year":1995,"vin":"1G6DV5EP4C0051515"},
{"id":606,"car_make":"Saab","car_model":"9-5","year":2001,"vin":"1N4AL2AP0BC567643"},
{"id":607,"car_make":"Chrysler","car_model":"Town & Country","year":1996,"vin":"WAUHF98P17A956712"},
{"id":608,"car_make":"BMW","car_model":"Z3","year":2000,"vin":"4USBT335X4L696583"},
{"id":609,"car_make":"Plymouth","car_model":"Colt Vista","year":1993,"vin":"4T1BF3EK9BU651718"},
{"id":610,"car_make":"Pontiac","car_model":"Sunbird","year":1992,"vin":"1G6KD54Y52U049235"},
{"id":611,"car_make":"Buick","car_model":"Park Avenue","year":1997,"vin":"5NPE24AFXFH526447"},
{"id":612,"car_make":"Kia","car_model":"Sportage","year":2002,"vin":"1GYFC23279R426619"},
{"id":613,"car_make":"Pontiac","car_model":"Bonneville","year":1968,"vin":"3C63D2EL7CG068397"},
{"id":614,"car_make":"Chrysler","car_model":"PT Cruiser","year":2004,"vin":"1GD220CG5CZ942553"},
{"id":615,"car_make":"Ford","car_model":"E-Series","year":1986,"vin":"TRUTC28N511438806"},
{"id":616,"car_make":"Audi","car_model":"RS 4","year":2008,"vin":"1G6DS8EDXB0339568"},
{"id":617,"car_make":"Dodge","car_model":"Magnum","year":2006,"vin":"WA1EY94L57D797799"},
{"id":618,"car_make":"Saab","car_model":"9000","year":1987,"vin":"1GYEE637X90653753"},
{"id":619,"car_make":"Hyundai","car_model":"Santa Fe","year":2005,"vin":"WA1MMAFE3AD435100"},
{"id":620,"car_make":"Mazda","car_model":"MX-5","year":1996,"vin":"1G6DL1EDXB0604476"},
{"id":621,"car_make":"Pontiac","car_model":"Solstice","year":2007,"vin":"JN1AZ4EHXBM854573"},
{"id":622,"car_make":"Ford","car_model":"Fusion","year":2007,"vin":"WUARL48H94K912834"},
{"id":623,"car_make":"Buick","car_model":"Regal","year":2004,"vin":"WBS3C9C57FJ323716"},
{"id":624,"car_make":"Pontiac","car_model":"LeMans","year":1991,"vin":"WUAW2AFCXFN520300"},
{"id":625,"car_make":"GMC","car_model":"Suburban 1500","year":1998,"vin":"1G6KD57959U550317"},
{"id":626,"car_make":"Alfa Romeo","car_model":"164","year":1993,"vin":"WAUKD78P47A800390"},
{"id":627,"car_make":"Honda","car_model":"Accord","year":1990,"vin":"WBANW13549C971335"},
{"id":628,"car_make":"Plymouth","car_model":"Prowler","year":2000,"vin":"JTHBL1EF3B5762309"},
{"id":629,"car_make":"Nissan","car_model":"Armada","year":2005,"vin":"2HNYD18936H249858"},
{"id":630,"car_make":"Mazda","car_model":"Tribute","year":2011,"vin":"1G6AH5SX5E0601869"},
{"id":631,"car_make":"Porsche","car_model":"944","year":1989,"vin":"5TDBM5G14BS689999"},
{"id":632,"car_make":"Dodge","car_model":"Dakota","year":2004,"vin":"1B3CB4HA5AD684616"},
{"id":633,"car_make":"Lotus","car_model":"Esprit","year":1994,"vin":"SCBLC37FX5C791789"},
{"id":634,"car_make":"Subaru","car_model":"Outback","year":2005,"vin":"WAUSGAFC7CN836839"},
{"id":635,"car_make":"Ferrari","car_model":"599 GTB Fiorano","year":2010,"vin":"1GYS4NKJ4FR310330"},
{"id":636,"car_make":"Ford","car_model":"Focus","year":2012,"vin":"JN8AF5MR3ET889041"},
{"id":637,"car_make":"Mercury","car_model":"Villager","year":1999,"vin":"1FADP5CU0EL066407"},
{"id":638,"car_make":"Ford","car_model":"Econoline E150","year":2000,"vin":"19XFB2F55FE965777"},
{"id":639,"car_make":"Ford","car_model":"LTD Crown Victoria","year":1988,"vin":"WBSWD93559P098188"},
{"id":640,"car_make":"Cadillac","car_model":"Escalade ESV","year":2009,"vin":"1G6AZ5SX1E0005638"},
{"id":641,"car_make":"Ferrari","car_model":"599 GTB Fiorano","year":2009,"vin":"1G6DV1EP7E0193434"},
{"id":642,"car_make":"Cadillac","car_model":"Escalade EXT","year":2003,"vin":"1C4AJWAG3FL655275"},
{"id":643,"car_make":"Lexus","car_model":"RX","year":2012,"vin":"WAUFFAFC2DN165151"},
{"id":644,"car_make":"Mazda","car_model":"Navajo","year":1992,"vin":"WAUHF78P08A301768"},
{"id":645,"car_make":"Maybach","car_model":"62","year":2008,"vin":"WAUBF78E37A968482"},
{"id":646,"car_make":"Dodge","car_model":"Viper","year":2005,"vin":"1D7RV1CT3AS718335"},
{"id":647,"car_make":"Mercedes-Benz","car_model":"SLS-Class","year":2011,"vin":"3D73Y4CL5BG552827"},
{"id":648,"car_make":"Jaguar","car_model":"XJ","year":2012,"vin":"1C3BCBEB0DN754728"},
{"id":649,"car_make":"Isuzu","car_model":"VehiCROSS","year":1999,"vin":"3VW467AT9DM045469"},
{"id":650,"car_make":"Buick","car_model":"Skylark","year":1997,"vin":"WBAYB6C5XED837973"},
{"id":651,"car_make":"Mercedes-Benz","car_model":"SLS-Class","year":2012,"vin":"2C4RDGCG6DR355179"},
{"id":652,"car_make":"Kia","car_model":"Sephia","year":1994,"vin":"WAULC58E92A857574"},
{"id":653,"car_make":"Pontiac","car_model":"Firebird","year":1988,"vin":"WBAEB53589C021384"},
{"id":654,"car_make":"Mazda","car_model":"MX-5","year":2001,"vin":"WBAVS13527F380234"},
{"id":655,"car_make":"Lincoln","car_model":"Navigator L","year":2010,"vin":"5N1AR1NB2AC094128"},
{"id":656,"car_make":"Pontiac","car_model":"Grand Am","year":2003,"vin":"5N1AN0NW5EN184196"},
{"id":657,"car_make":"Dodge","car_model":"Journey","year":2010,"vin":"JN1CV6FE4BM096315"},
{"id":658,"car_make":"Chevrolet","car_model":"Suburban 2500","year":1996,"vin":"JN8AZ2KR8CT686636"},
{"id":659,"car_make":"Buick","car_model":"Century","year":1984,"vin":"JN8AS5MTXAW123758"},
{"id":660,"car_make":"Chevrolet","car_model":"Cavalier","year":1996,"vin":"WAUFFBFL3BN101574"},
{"id":661,"car_make":"Chevrolet","car_model":"Express 3500","year":2007,"vin":"WBAEU33433P651626"},
{"id":662,"car_make":"Bentley","car_model":"Azure","year":2007,"vin":"WAUBFAFLXCA384346"},
{"id":663,"car_make":"BMW","car_model":"8 Series","year":1992,"vin":"1D4PU6GX6AW566173"},
{"id":664,"car_make":"Ford","car_model":"Expedition","year":2000,"vin":"1G6DM577X90751273"},
{"id":665,"car_make":"GMC","car_model":"3500","year":1999,"vin":"1G6DM1ED7B0426751"},
{"id":666,"car_make":"Toyota","car_model":"Sequoia","year":2009,"vin":"1GYS4KEF2DR872469"},
{"id":667,"car_make":"Plymouth","car_model":"Colt","year":1993,"vin":"JM1BL1L33D1877898"},
{"id":668,"car_make":"Dodge","car_model":"Grand Caravan","year":1996,"vin":"1GYS3GEF7CR929425"},
{"id":669,"car_make":"Dodge","car_model":"Journey","year":2009,"vin":"5GADT13S142643190"},
{"id":670,"car_make":"Pontiac","car_model":"Grand Am","year":1985,"vin":"WVGEF9BP2ED519713"},
{"id":671,"car_make":"Subaru","car_model":"Outback","year":2010,"vin":"1G4HH5E97AU497022"},
{"id":672,"car_make":"Hyundai","car_model":"Sonata","year":1992,"vin":"WAUBFAFL2EN889891"},
{"id":673,"car_make":"Chevrolet","car_model":"Corvette","year":2002,"vin":"JN1CV6AP4AM862292"},
{"id":674,"car_make":"Geo","car_model":"Prizm","year":1997,"vin":"5XXGM4A70EG513194"},
{"id":675,"car_make":"Maybach","car_model":"62","year":2008,"vin":"WAUKH98E96A005798"},
{"id":676,"car_make":"Nissan","car_model":"Altima","year":2004,"vin":"1G6AC1RX8F0753983"},
{"id":677,"car_make":"Chevrolet","car_model":"Express 1500","year":2000,"vin":"WA1CGAFE9ED332532"},
{"id":678,"car_make":"Chevrolet","car_model":"Express 2500","year":2003,"vin":"1FMJK1HT3FE307847"},
{"id":679,"car_make":"Honda","car_model":"del Sol","year":1997,"vin":"WBABW53465P223142"},
{"id":680,"car_make":"Mazda","car_model":"MX-5","year":2002,"vin":"JTJHY7AXXF4856680"},
{"id":681,"car_make":"Chrysler","car_model":"PT Cruiser","year":2002,"vin":"YV1672MW9B2399833"},
{"id":682,"car_make":"Maserati","car_model":"Gran Sport","year":2006,"vin":"JTHBW1GG6E1157421"},
{"id":683,"car_make":"Mazda","car_model":"B-Series Plus","year":1998,"vin":"JN8AZ2KR8DT095112"},
{"id":684,"car_make":"Chevrolet","car_model":"Corvette","year":1999,"vin":"2FMDK3KCXAB968314"},
{"id":685,"car_make":"Volvo","car_model":"V70","year":2001,"vin":"WA1WMAFE1DD359213"},
{"id":686,"car_make":"Rolls-Royce","car_model":"Ghost","year":2011,"vin":"2B3CK2CV9AH390928"},
{"id":687,"car_make":"Dodge","car_model":"Ram 50","year":1992,"vin":"2CTALMECXB6128122"},
{"id":688,"car_make":"Chevrolet","car_model":"Monte Carlo","year":2002,"vin":"WAUXU64B63N929891"},
{"id":689,"car_make":"Chevrolet","car_model":"Suburban 2500","year":2001,"vin":"KMHHT6KD2AU214670"},
{"id":690,"car_make":"Volvo","car_model":"S40","year":2000,"vin":"1YVHZ8BH5A5609870"},
{"id":691,"car_make":"GMC","car_model":"Savana 2500","year":2000,"vin":"5N1AT2ML4EC840585"},
{"id":692,"car_make":"Chevrolet","car_model":"Silverado 1500","year":1999,"vin":"KNAFT4A25A5400467"},
{"id":693,"car_make":"Toyota","car_model":"Sienna","year":2007,"vin":"WDDGF4HB3ER590049"},
{"id":694,"car_make":"Audi","car_model":"A6","year":1996,"vin":"KNDJT2A29D7272261"},
{"id":695,"car_make":"Saturn","car_model":"L-Series","year":2003,"vin":"JN1CV6AP2FM728162"},
{"id":696,"car_make":"Mitsubishi","car_model":"GTO","year":1996,"vin":"1G6AB5SX5E0254125"},
{"id":697,"car_make":"Mazda","car_model":"Mazda6 5-Door","year":2006,"vin":"JTDJTUD39ED309330"},
{"id":698,"car_make":"Mercury","car_model":"Milan","year":2009,"vin":"3G5DB03E44S361577"},
{"id":699,"car_make":"Chevrolet","car_model":"Sportvan G10","year":1993,"vin":"YV126MFK1F2529424"},
{"id":700,"car_make":"Infiniti","car_model":"J","year":1993,"vin":"1N6AF0KX9EN197920"},
{"id":701,"car_make":"Acura","car_model":"RL","year":2001,"vin":"SCFLDCFP8EG736885"},
{"id":702,"car_make":"Mercedes-Benz","car_model":"CL65 AMG","year":2009,"vin":"1D7RW2GK6BS514697"},
{"id":703,"car_make":"Bentley","car_model":"Continental Flying Spur","year":2007,"vin":"3GYFNHE30DS801078"},
{"id":704,"car_make":"Mercedes-Benz","car_model":"CL-Class","year":2010,"vin":"JN1CV6FE7FM198441"},
{"id":705,"car_make":"GMC","car_model":"Vandura 1500","year":1994,"vin":"WBA6B2C54FD355940"},
{"id":706,"car_make":"Toyota","car_model":"4Runner","year":1992,"vin":"WAULC68E45A619934"},
{"id":707,"car_make":"GMC","car_model":"Yukon XL 2500","year":2002,"vin":"WVWAB7AJ5DW748728"},
{"id":708,"car_make":"Saab","car_model":"900","year":1994,"vin":"2FMDK4JC6AB436856"},
{"id":709,"car_make":"BMW","car_model":"525","year":2004,"vin":"2C3CDXDT2DH265751"},
{"id":710,"car_make":"GMC","car_model":"3500 Club Coupe","year":1994,"vin":"3C3CFFHH6DT083780"},
{"id":711,"car_make":"BMW","car_model":"5 Series","year":2008,"vin":"WAULC58E95A095156"},
{"id":712,"car_make":"Buick","car_model":"Electra","year":1988,"vin":"JTHCL5EF5F5578197"},
{"id":713,"car_make":"GMC","car_model":"2500 Club Coupe","year":1997,"vin":"1VWAH7A37EC045762"},
{"id":714,"car_make":"Mercury","car_model":"Grand Marquis","year":2001,"vin":"WAULT58E72A643084"},
{"id":715,"car_make":"Toyota","car_model":"RAV4","year":2005,"vin":"1FTSW2A54AE087240"},
{"id":716,"car_make":"Pontiac","car_model":"Bonneville","year":1998,"vin":"1C4RJEAG1EC347288"},
{"id":717,"car_make":"Buick","car_model":"Skylark","year":1995,"vin":"3D73M4HL8BG142155"},
{"id":718,"car_make":"Lotus","car_model":"Elan","year":1992,"vin":"JM3TB2CV9F0061471"},
{"id":719,"car_make":"Mitsubishi","car_model":"Eclipse","year":2002,"vin":"1D4PU6GX0AW986799"},
{"id":720,"car_make":"GMC","car_model":"Jimmy","year":1994,"vin":"1C3CDZAB5DN037807"},
{"id":721,"car_make":"Buick","car_model":"Regal","year":1993,"vin":"1FMEU6EE8AU045028"},
{"id":722,"car_make":"Aston Martin","car_model":"Vanquish S","year":2005,"vin":"2D4RN4DEXAR729400"},
{"id":723,"car_make":"Ford","car_model":"Escort","year":1990,"vin":"WAUSF78E27A806178"},
{"id":724,"car_make":"Pontiac","car_model":"G6","year":2008,"vin":"1D4PT2GK3BW837837"},
{"id":725,"car_make":"Nissan","car_model":"350Z","year":2006,"vin":"1D4PU4GK8AW251254"},
{"id":726,"car_make":"Dodge","car_model":"Charger","year":2009,"vin":"1G6AM5SXXE0706046"},
{"id":727,"car_make":"Acura","car_model":"TSX","year":2005,"vin":"WAUDL54F35N506806"},
{"id":728,"car_make":"Ford","car_model":"E150","year":2005,"vin":"WA1VMBFE7BD164778"},
{"id":729,"car_make":"Mitsubishi","car_model":"Outlander","year":2008,"vin":"3GYFNEE36DS131003"},
{"id":730,"car_make":"Plymouth","car_model":"Laser","year":1994,"vin":"4F2CY0C77BK353857"},
{"id":731,"car_make":"Mercury","car_model":"Sable","year":1999,"vin":"3VW517AT6EM232222"},
{"id":732,"car_make":"Infiniti","car_model":"M","year":2006,"vin":"2G4WC582871263352"},
{"id":733,"car_make":"Pontiac","car_model":"Sunbird","year":1988,"vin":"WA1BY74L48D221503"},
{"id":734,"car_make":"Chevrolet","car_model":"Express","year":2010,"vin":"1FTEX1EW9AF723961"},
{"id":735,"car_make":"Subaru","car_model":"Justy","year":1987,"vin":"WA1LFBFP4EA677852"},
{"id":736,"car_make":"Dodge","car_model":"Ram Van 1500","year":1999,"vin":"SCBGT3ZA9EC595622"},
{"id":737,"car_make":"Land Rover","car_model":"Freelander","year":2009,"vin":"1G4GE5ED1BF391809"},
{"id":738,"car_make":"Chevrolet","car_model":"Express 3500","year":2001,"vin":"WAUVT68E15A971569"},
{"id":739,"car_make":"Dodge","car_model":"Viper","year":2003,"vin":"JTEBU5JR0E5093261"},
{"id":740,"car_make":"Ford","car_model":"F350","year":2012,"vin":"WAU2GAFC3CN697342"},
{"id":741,"car_make":"BMW","car_model":"600","year":1957,"vin":"JH4CU2E68AC081189"},
{"id":742,"car_make":"Plymouth","car_model":"Reliant","year":1981,"vin":"1FTEW1CW1AK973465"},
{"id":743,"car_make":"Maybach","car_model":"57","year":2007,"vin":"WAULT68E14A297476"},
{"id":744,"car_make":"Subaru","car_model":"Legacy","year":1998,"vin":"KNAGN4ADXF5520580"},
{"id":745,"car_make":"Chevrolet","car_model":"Express 2500","year":2000,"vin":"JA32X8HW0EU388101"},
{"id":746,"car_make":"Suzuki","car_model":"Esteem","year":2001,"vin":"YV1612FS3E1430077"},
{"id":747,"car_make":"Chrysler","car_model":"Crossfire Roadster","year":2006,"vin":"JN1CV6EK9EM916612"},
{"id":748,"car_make":"Suzuki","car_model":"Reno","year":2005,"vin":"WDDEJ7GB2AA294912"},
{"id":749,"car_make":"Maserati","car_model":"Spyder","year":2002,"vin":"3C4PDCDG1FT175610"},
{"id":750,"car_make":"Ford","car_model":"Th!nk","year":2000,"vin":"WAUUFAFH1BN095349"},
{"id":751,"car_make":"Mazda","car_model":"B-Series","year":2004,"vin":"5J6TF2H51FL676028"},
{"id":752,"car_make":"Dodge","car_model":"Caravan","year":1999,"vin":"WAUJF78KX9N295140"},
{"id":753,"car_make":"Dodge","car_model":"Charger","year":2009,"vin":"WAUWFAFH5EN247534"},
{"id":754,"car_make":"Ford","car_model":"Freestyle","year":2006,"vin":"WAUNF98P46A885118"},
{"id":755,"car_make":"Acura","car_model":"TL","year":2008,"vin":"SAJWA4GC4EM131884"},
{"id":756,"car_make":"Suzuki","car_model":"SX4","year":2011,"vin":"1D4RD3GG2BC607845"},
{"id":757,"car_make":"Nissan","car_model":"Pathfinder","year":2002,"vin":"JH4CU2F83DC781013"},
{"id":758,"car_make":"Mercedes-Benz","car_model":"C-Class","year":2001,"vin":"JN1CV6EK4FM816631"},
{"id":759,"car_make":"Honda","car_model":"Prelude","year":2001,"vin":"WBA3V5C57F5866922"},
{"id":760,"car_make":"Mazda","car_model":"Tribute","year":2006,"vin":"WBAUL7C51CV590691"},
{"id":761,"car_make":"Dodge","car_model":"Stratus","year":1996,"vin":"WAUEH98E77A009248"},
{"id":762,"car_make":"Mazda","car_model":"Mazda6","year":2011,"vin":"SAJWA4EC6BM229426"},
{"id":763,"car_make":"GMC","car_model":"Terrain","year":2011,"vin":"WAUWMAFC4EN337705"},
{"id":764,"car_make":"Audi","car_model":"TT","year":2010,"vin":"SCFEBBCF0BG360957"},
{"id":765,"car_make":"BMW","car_model":"Z8","year":2002,"vin":"WAUHF98P67A266521"},
{"id":766,"car_make":"Ford","car_model":"Ranger","year":2004,"vin":"1D7CW3BK6AS680669"},
{"id":767,"car_make":"Hyundai","car_model":"Tucson","year":2012,"vin":"2G4GR5GX0F9044644"},
{"id":768,"car_make":"Mitsubishi","car_model":"Outlander Sport","year":2011,"vin":"WDDLJ7DB0EA198634"},
{"id":769,"car_make":"Audi","car_model":"Quattro","year":1985,"vin":"WVGAV3AX0DW598852"},
{"id":770,"car_make":"Suzuki","car_model":"Swift","year":1995,"vin":"3C6JD6CT6CG080705"},
{"id":771,"car_make":"Porsche","car_model":"924","year":1988,"vin":"WA1WMBFEXFD396771"},
{"id":772,"car_make":"Mercedes-Benz","car_model":"SL-Class","year":1986,"vin":"YV1952AS0E1939651"},
{"id":773,"car_make":"Subaru","car_model":"Legacy","year":2009,"vin":"WBAYB6C52DC293005"},
{"id":774,"car_make":"Lincoln","car_model":"Town Car","year":1990,"vin":"1FMCU4K30CK221695"},
{"id":775,"car_make":"Lexus","car_model":"LS","year":2000,"vin":"WAUWGBFB8BN579199"},
{"id":776,"car_make":"Pontiac","car_model":"6000","year":1990,"vin":"WBAVL1C5XFV382315"},
{"id":777,"car_make":"Lincoln","car_model":"LS","year":2004,"vin":"WAUAF98E65A450290"},
{"id":778,"car_make":"GMC","car_model":"Yukon","year":2003,"vin":"JTDKN3DU4A0501449"},
{"id":779,"car_make":"Chevrolet","car_model":"Corvette","year":1985,"vin":"YV1902MC6F1101130"},
{"id":780,"car_make":"Subaru","car_model":"Alcyone SVX","year":1997,"vin":"5FRYD4H44EB870783"},
{"id":781,"car_make":"Lexus","car_model":"ES","year":1991,"vin":"WVWAN7AN4EE715091"},
{"id":782,"car_make":"Pontiac","car_model":"G5","year":2009,"vin":"KMHEC4A49EA261355"},
{"id":783,"car_make":"GMC","car_model":"Vandura 3500","year":1994,"vin":"WA1WMBFE1DD557330"},
{"id":784,"car_make":"GMC","car_model":"Suburban 1500","year":1994,"vin":"5LMJJ2H50EE194500"},
{"id":785,"car_make":"Lincoln","car_model":"MKS","year":2011,"vin":"5NMSG3AB7AH376850"},
{"id":786,"car_make":"Scion","car_model":"tC","year":2013,"vin":"WDDEJ7KB3CA857945"},
{"id":787,"car_make":"Bentley","car_model":"Continental Flying Spur","year":2012,"vin":"1G4PP5SKXC4325768"},
{"id":788,"car_make":"Mazda","car_model":"Mazda6","year":2003,"vin":"WP1AE2A2XEL913237"},
{"id":789,"car_make":"Pontiac","car_model":"GTO","year":1968,"vin":"WAUSGCFC7CN787749"},
{"id":790,"car_make":"Jeep","car_model":"Cherokee","year":1992,"vin":"JN8AZ1FY8CW406661"},
{"id":791,"car_make":"Dodge","car_model":"Ram 50","year":1992,"vin":"3VWML7AJ0CM563251"},
{"id":792,"car_make":"Lexus","car_model":"LS","year":2011,"vin":"YV140MEB7F1121141"},
{"id":793,"car_make":"Toyota","car_model":"Tercel","year":1996,"vin":"KMHTC6AD2EU124078"},
{"id":794,"car_make":"Mercury","car_model":"Monterey","year":2005,"vin":"KNAGM4A78B5271400"},
{"id":795,"car_make":"Hummer","car_model":"H3","year":2007,"vin":"4JGBF2FB4AA984241"},
{"id":796,"car_make":"Pontiac","car_model":"Grand Prix","year":1978,"vin":"5TDDK3DC0CS446698"},
{"id":797,"car_make":"Cadillac","car_model":"DeVille","year":1995,"vin":"WA1WMBFE4DD698764"},
{"id":798,"car_make":"Chevrolet","car_model":"Sportvan G30","year":1992,"vin":"1FTMF1CW9AK907306"},
{"id":799,"car_make":"Mercury","car_model":"Grand Marquis","year":2006,"vin":"JTDKN3DP3E3254052"},
{"id":800,"car_make":"Dodge","car_model":"Dakota","year":2001,"vin":"WAUDG74F06N917453"},
{"id":801,"car_make":"Mercury","car_model":"Cougar","year":1997,"vin":"5J6TF1H37DL862646"},
{"id":802,"car_make":"Kia","car_model":"Optima","year":2012,"vin":"WBAWB3C56AP642743"},
{"id":803,"car_make":"Pontiac","car_model":"Bonneville","year":1995,"vin":"2C4RDGDG6CR520161"},
{"id":804,"car_make":"Lotus","car_model":"Esprit","year":1997,"vin":"19UYA42601A994543"},
{"id":805,"car_make":"Land Rover","car_model":"Defender 90","year":1997,"vin":"2HKRM3H33CH182537"},
{"id":806,"car_make":"GMC","car_model":"Savana 3500","year":2001,"vin":"4T1BF3EK6AU262128"},
{"id":807,"car_make":"Mercedes-Benz","car_model":"C-Class","year":1997,"vin":"3GTU2YEJ1DG624676"},
{"id":808,"car_make":"Pontiac","car_model":"Grand Am","year":2005,"vin":"1FTMF1E85AF453191"},
{"id":809,"car_make":"Porsche","car_model":"Boxster","year":2013,"vin":"WP1AA2A20BL785663"},
{"id":810,"car_make":"Lincoln","car_model":"Mark VIII","year":1993,"vin":"WAUGL98E77A572453"},
{"id":811,"car_make":"Dodge","car_model":"Ram Van 1500","year":1996,"vin":"WP0CB2A8XCS635811"},
{"id":812,"car_make":"Pontiac","car_model":"Gemini","year":1986,"vin":"JTDKN3DU2A0041689"},
{"id":813,"car_make":"Volkswagen","car_model":"Touareg","year":2004,"vin":"WAUJT64B43N561980"},
{"id":814,"car_make":"Land Rover","car_model":"LR3","year":2006,"vin":"2T1BU4EEXDC079049"},
{"id":815,"car_make":"Mercedes-Benz","car_model":"CLS-Class","year":2007,"vin":"1G4HG5EM8AU482942"},
{"id":816,"car_make":"Buick","car_model":"Roadmaster","year":1995,"vin":"2G61P5S37F9969591"},
{"id":817,"car_make":"Honda","car_model":"CR-Z","year":2011,"vin":"KMHEC4A49EA875628"},
{"id":818,"car_make":"Ford","car_model":"Econoline E150","year":1994,"vin":"WAUBF98E68A737993"},
{"id":819,"car_make":"Ford","car_model":"Econoline E250","year":1994,"vin":"3D7JB1EK8BG459957"},
{"id":820,"car_make":"Chevrolet","car_model":"Suburban","year":2009,"vin":"WBAEH13486C085757"},
{"id":821,"car_make":"Audi","car_model":"5000CS Quattro","year":1986,"vin":"WBAXH5C54CC573303"},
{"id":822,"car_make":"Porsche","car_model":"911","year":1997,"vin":"1N6AA0CC2CN190475"},
{"id":823,"car_make":"Pontiac","car_model":"Grand Am","year":1989,"vin":"1N4AL3APXEC909979"},
{"id":824,"car_make":"Mitsubishi","car_model":"Pajero","year":1999,"vin":"WA1CFAFP2BA829813"},
{"id":825,"car_make":"Jaguar","car_model":"XF","year":2012,"vin":"2HNYD28828H425721"},
{"id":826,"car_make":"Lexus","car_model":"HS","year":2011,"vin":"1N4AL2AP4AN706014"},
{"id":827,"car_make":"Honda","car_model":"FCX Clarity","year":2012,"vin":"3C3CFFBR6FT369147"},
{"id":828,"car_make":"Mitsubishi","car_model":"Truck","year":1990,"vin":"WBA5A5C57ED814442"},
{"id":829,"car_make":"Toyota","car_model":"Tundra","year":2011,"vin":"1N6AA0CC7EN084722"},
{"id":830,"car_make":"GMC","car_model":"Savana 2500","year":2001,"vin":"5GALRBED6AJ173383"},
{"id":831,"car_make":"Mercedes-Benz","car_model":"S-Class","year":1985,"vin":"3N1AB6AP1AL091218"},
{"id":832,"car_make":"Mitsubishi","car_model":"3000GT","year":1998,"vin":"WBA3G7C55FK538177"},
{"id":833,"car_make":"Toyota","car_model":"TundraMax","year":2012,"vin":"1FTWW3B52AE245614"},
{"id":834,"car_make":"Audi","car_model":"A4","year":2000,"vin":"2LMDJ6JK0BB179496"},
{"id":835,"car_make":"Dodge","car_model":"Dakota Club","year":1995,"vin":"WVGAV3AX6EW772019"},
{"id":836,"car_make":"Volvo","car_model":"V50","year":2011,"vin":"KMHEC4A43DA954145"},
{"id":837,"car_make":"Ford","car_model":"Explorer Sport Trac","year":2009,"vin":"5J8TB3H34GL909263"},
{"id":838,"car_make":"Dodge","car_model":"Ram 2500","year":2010,"vin":"JH4CL96987C476681"},
{"id":839,"car_make":"Volvo","car_model":"S40","year":2004,"vin":"SCFEBBCF2CG272123"},
{"id":840,"car_make":"Lexus","car_model":"LX","year":2004,"vin":"5N1AA0NC1EN649347"},
{"id":841,"car_make":"Lexus","car_model":"LS","year":2003,"vin":"3VWA17AU8FM260063"},
{"id":842,"car_make":"Dodge","car_model":"Journey","year":2010,"vin":"SCFFDCBD0CG182635"},
{"id":843,"car_make":"Jaguar","car_model":"XJ","year":2010,"vin":"1YVHZ8BH8A5197623"},
{"id":844,"car_make":"Chevrolet","car_model":"Express 2500","year":2007,"vin":"2T2BC1BA8FC040025"},
{"id":845,"car_make":"Mazda","car_model":"626","year":1983,"vin":"3C4PDCAB5FT344567"},
{"id":846,"car_make":"Ford","car_model":"Galaxie","year":1966,"vin":"1B3CB3HA9BD271934"},
{"id":847,"car_make":"Chevrolet","car_model":"Camaro","year":1978,"vin":"1GD422CGXEF838939"},
{"id":848,"car_make":"Mercedes-Benz","car_model":"Sprinter 3500","year":2012,"vin":"1G6DM5EY9B0972431"},
{"id":849,"car_make":"Ford","car_model":"F-Series","year":1991,"vin":"5GAKVAKD0EJ444918"},
{"id":850,"car_make":"Acura","car_model":"SLX","year":1997,"vin":"1D7RW3BKXAS841972"},
{"id":851,"car_make":"Cadillac","car_model":"CTS-V","year":2012,"vin":"WBAAV53471F421906"},
{"id":852,"car_make":"Mercedes-Benz","car_model":"300CE","year":1993,"vin":"WAULC58E73A128555"},
{"id":853,"car_make":"Mitsubishi","car_model":"Tredia","year":1986,"vin":"WA1CGBFE3BD123532"},
{"id":854,"car_make":"Isuzu","car_model":"Trooper","year":1997,"vin":"5J6TF2H51FL417264"},
{"id":855,"car_make":"Mazda","car_model":"MX-5","year":1995,"vin":"3GYFNGE30CS607255"},
{"id":856,"car_make":"Suzuki","car_model":"Grand Vitara","year":1999,"vin":"2G61L5S38E9856808"},
{"id":857,"car_make":"Mercedes-Benz","car_model":"W201","year":1991,"vin":"1YVHZ8BH1A5527926"},
{"id":858,"car_make":"Lincoln","car_model":"MKX","year":2013,"vin":"WBAWB735X8P158219"},
{"id":859,"car_make":"Plymouth","car_model":"Neon","year":1997,"vin":"1G6DU6EV3A0764930"},
{"id":860,"car_make":"Mercury","car_model":"Cougar","year":1967,"vin":"WAUWFBFL7CA910293"},
{"id":861,"car_make":"Mazda","car_model":"Mazda5","year":2010,"vin":"WAULFAFR8EA624814"},
{"id":862,"car_make":"Ford","car_model":"Ranger","year":1999,"vin":"SCBGT3ZA7FC914338"},
{"id":863,"car_make":"Suzuki","car_model":"Swift","year":2006,"vin":"1G4GE5ED1BF818308"},
{"id":864,"car_make":"Nissan","car_model":"Sentra","year":2008,"vin":"JN8AZ2KR4CT689601"},
{"id":865,"car_make":"Kia","car_model":"Carens","year":2009,"vin":"JTHBW1GG4F2825910"},
{"id":866,"car_make":"Infiniti","car_model":"G","year":2010,"vin":"WBAPH57589N422214"},
{"id":867,"car_make":"Chrysler","car_model":"Concorde","year":1998,"vin":"5N1AA0NCXCN674924"},
{"id":868,"car_make":"Nissan","car_model":"GT-R","year":2013,"vin":"2D4RN5DG3BR170197"},
{"id":869,"car_make":"Lamborghini","car_model":"Diablo","year":1998,"vin":"2C4RDGAG3CR525189"},
{"id":870,"car_make":"Hyundai","car_model":"Sonata","year":2006,"vin":"WBAKF3C50CE220680"},
{"id":871,"car_make":"Dodge","car_model":"Ram 1500","year":2007,"vin":"JH4DC53092C501986"},
{"id":872,"car_make":"Honda","car_model":"Odyssey","year":1997,"vin":"5UXKR0C53E0500407"},
{"id":873,"car_make":"Chevrolet","car_model":"TrailBlazer","year":2008,"vin":"1GYFC532X9R225153"},
{"id":874,"car_make":"Pontiac","car_model":"Trans Sport","year":1993,"vin":"JTHBE1D23F5776967"},
{"id":875,"car_make":"Dodge","car_model":"Shadow","year":1994,"vin":"5GADT13S942108169"},
{"id":876,"car_make":"Mitsubishi","car_model":"Expo","year":1995,"vin":"WAUVT64B82N669342"},
{"id":877,"car_make":"Ford","car_model":"Bronco","year":1994,"vin":"2LMDJ6JK0DB623835"},
{"id":878,"car_make":"GMC","car_model":"Envoy XL","year":2002,"vin":"5J8TB4H37FL700457"},
{"id":879,"car_make":"Lincoln","car_model":"Navigator L","year":2009,"vin":"1FTSX2A59AE633379"},
{"id":880,"car_make":"Audi","car_model":"S8","year":2002,"vin":"WBAAZ33444K370255"},
{"id":881,"car_make":"Nissan","car_model":"Versa","year":2011,"vin":"1FMCU0C70BK163189"},
{"id":882,"car_make":"Spyker","car_model":"C8","year":2007,"vin":"JA32U2FU7DU295078"},
{"id":883,"car_make":"Lincoln","car_model":"Mark VIII","year":1998,"vin":"1G6DH5EY8B0275448"},
{"id":884,"car_make":"BMW","car_model":"5 Series","year":1999,"vin":"5N1AT2ML7EC552575"},
{"id":885,"car_make":"Citroën","car_model":"CX","year":1989,"vin":"2D4RN3D1XAR698303"},
{"id":886,"car_make":"GMC","car_model":"Sierra 3500","year":2000,"vin":"WBA3N7C54FK924207"},
{"id":887,"car_make":"Chevrolet","car_model":"Camaro","year":1971,"vin":"1FTWW3B53AE000336"},
{"id":888,"car_make":"Ford","car_model":"Excursion","year":2003,"vin":"NM0KS9BN1BT921349"},
{"id":889,"car_make":"Volkswagen","car_model":"New Beetle","year":2012,"vin":"2G61V5S88F9277762"},
{"id":890,"car_make":"Honda","car_model":"Accord","year":1983,"vin":"WBA6B8C51FD809502"},
{"id":891,"car_make":"Maserati","car_model":"Spyder","year":2004,"vin":"WAUCFAFC0FN514586"},
{"id":892,"car_make":"Chevrolet","car_model":"S10","year":2002,"vin":"SCBZB25E92C531350"},
{"id":893,"car_make":"Maybach","car_model":"Landaulet","year":2010,"vin":"WBS3C9C5XFP596565"},
{"id":894,"car_make":"Chrysler","car_model":"Imperial","year":1993,"vin":"3VWML7AJ1CM650219"},
{"id":895,"car_make":"Honda","car_model":"Civic","year":1989,"vin":"JN8AF5MR8DT994253"},
{"id":896,"car_make":"Cadillac","car_model":"Escalade ESV","year":2008,"vin":"KM8NU4CC6AU984896"},
{"id":897,"car_make":"Subaru","car_model":"Justy","year":1991,"vin":"SCBGR3ZAXCC702415"},
{"id":898,"car_make":"Mitsubishi","car_model":"L300","year":1987,"vin":"5J8TB4H74GL459431"},
{"id":899,"car_make":"Volvo","car_model":"C70","year":2012,"vin":"2C4RDGCG0ER704211"},
{"id":900,"car_make":"Audi","car_model":"A4","year":1996,"vin":"JTDZN3EU4EJ599718"},
{"id":901,"car_make":"Mazda","car_model":"Navajo","year":1993,"vin":"1G6DU57VX90315764"},
{"id":902,"car_make":"Honda","car_model":"Accord","year":2001,"vin":"2C3CDXL98FH395431"},
{"id":903,"car_make":"Ford","car_model":"LTD Crown Victoria","year":1987,"vin":"JM1BL1K5XB1179918"},
{"id":904,"car_make":"Kia","car_model":"Spectra","year":2009,"vin":"WAU4FAFR5AA075832"},
{"id":905,"car_make":"Chevrolet","car_model":"Suburban 1500","year":2004,"vin":"1GD01ZCG7CF918349"},
{"id":906,"car_make":"Chevrolet","car_model":"Malibu","year":2011,"vin":"WAUKGBFB8AN404528"},
{"id":907,"car_make":"Lexus","car_model":"SC","year":1998,"vin":"WBSBL93442J139783"},
{"id":908,"car_make":"Mitsubishi","car_model":"Mirage","year":1994,"vin":"WVWED7AJ0CW590843"},
{"id":909,"car_make":"Cadillac","car_model":"Escalade ESV","year":2009,"vin":"WAUML64B22N936714"},
{"id":910,"car_make":"Chevrolet","car_model":"Cruze","year":2012,"vin":"1FTEX1CM9DF039904"},
{"id":911,"car_make":"GMC","car_model":"Savana 3500","year":2011,"vin":"SALGS2DF3DA011439"},
{"id":912,"car_make":"Toyota","car_model":"Matrix","year":2011,"vin":"WAUFFBFL7BA490940"},
{"id":913,"car_make":"Pontiac","car_model":"Sunbird","year":1985,"vin":"SALAB2D44DA741509"},
{"id":914,"car_make":"Lamborghini","car_model":"Gallardo","year":2007,"vin":"1G4GC5EC2BF289268"},
{"id":915,"car_make":"Hummer","car_model":"H3","year":2006,"vin":"4T1BK1EB5FU932727"},
{"id":916,"car_make":"Audi","car_model":"90","year":1994,"vin":"WBA3A5C52FF553220"},
{"id":917,"car_make":"Ford","car_model":"E-Series","year":1994,"vin":"WAUSH78E38A314576"},
{"id":918,"car_make":"Mazda","car_model":"RX-7","year":1987,"vin":"2LMHJ5AR9BB341053"},
{"id":919,"car_make":"Mitsubishi","car_model":"Lancer","year":2002,"vin":"3VW467ATXCM913736"},
{"id":920,"car_make":"Chevrolet","car_model":"Tracker","year":2001,"vin":"5FNRL5H20EB663451"},
{"id":921,"car_make":"Infiniti","car_model":"IPL G","year":2012,"vin":"WBA3B5C54DP105971"},
{"id":922,"car_make":"Volkswagen","car_model":"Jetta","year":1996,"vin":"4A31K3DT3CE262393"},
{"id":923,"car_make":"GMC","car_model":"Yukon XL 2500","year":2003,"vin":"WBANE73576B522741"},
{"id":924,"car_make":"Volkswagen","car_model":"Cabriolet","year":1992,"vin":"WA1LMAFEXDD817382"},
{"id":925,"car_make":"Acura","car_model":"MDX","year":2006,"vin":"WAUDF48H67A384031"},
{"id":926,"car_make":"Ferrari","car_model":"599 GTB Fiorano","year":2007,"vin":"1FTSW2B51AE635029"},
{"id":927,"car_make":"Mazda","car_model":"MX-6","year":1991,"vin":"JN1CV6FE8EM887452"},
{"id":928,"car_make":"Honda","car_model":"S2000","year":2005,"vin":"WAUBFAFL0BN881669"},
{"id":929,"car_make":"Mazda","car_model":"B-Series Plus","year":1992,"vin":"5NPEB4AC9BH137136"},
{"id":930,"car_make":"Toyota","car_model":"Tundra","year":2001,"vin":"2C4RDGEG3FR533419"},
{"id":931,"car_make":"Audi","car_model":"Quattro","year":1993,"vin":"1FTFW1E81AK326132"},
{"id":932,"car_make":"GMC","car_model":"Suburban 1500","year":1999,"vin":"5NPDH4AE8DH995728"},
{"id":933,"car_make":"Mazda","car_model":"Millenia","year":1998,"vin":"WA1VMAFPXFA073958"},
{"id":934,"car_make":"Mazda","car_model":"Mazdaspeed6","year":2006,"vin":"WBAUN7C59CV941955"},
{"id":935,"car_make":"Bentley","car_model":"Arnage","year":2005,"vin":"KNADH5A34A6480457"},
{"id":936,"car_make":"Lamborghini","car_model":"Reventón","year":2008,"vin":"SALVN2BG4FH865859"},
{"id":937,"car_make":"Oldsmobile","car_model":"Achieva","year":1998,"vin":"19UUA65626A077181"},
{"id":938,"car_make":"Ferrari","car_model":"430 Scuderia","year":2009,"vin":"KMHGH4JH3DU371487"},
{"id":939,"car_make":"Dodge","car_model":"Challenger","year":2010,"vin":"WBAHN03577D300940"},
{"id":940,"car_make":"Chevrolet","car_model":"Metro","year":2000,"vin":"1G6AC5SX5D0911517"},
{"id":941,"car_make":"Saab","car_model":"900","year":1989,"vin":"WBAPN73529A989651"},
{"id":942,"car_make":"Chevrolet","car_model":"Colorado","year":2004,"vin":"1GYS3DEFXCR056882"},
{"id":943,"car_make":"Dodge","car_model":"Ram Van 3500","year":1999,"vin":"1GD312CG2BF337814"},
{"id":944,"car_make":"Ford","car_model":"Fusion","year":2007,"vin":"WBALW7C52CD819856"},
{"id":945,"car_make":"Volkswagen","car_model":"Golf","year":1989,"vin":"2FMDK4JC0AB821278"},
{"id":946,"car_make":"Jeep","car_model":"Grand Cherokee","year":1996,"vin":"2G61S5S38D9231097"},
{"id":947,"car_make":"Pontiac","car_model":"LeMans","year":1966,"vin":"1FTEW1CF3FF490124"},
{"id":948,"car_make":"Volkswagen","car_model":"Jetta III","year":1995,"vin":"1FTWW3B51AE051074"},
{"id":949,"car_make":"Pontiac","car_model":"Bonneville","year":1988,"vin":"SALFR2BN6AH342438"},
{"id":950,"car_make":"Mercedes-Benz","car_model":"SLK-Class","year":2009,"vin":"JN8AZ2KR9AT397472"},
{"id":951,"car_make":"Toyota","car_model":"Previa","year":1992,"vin":"3C6JD6CTXCG928813"},
{"id":952,"car_make":"Toyota","car_model":"Corolla","year":1993,"vin":"SCFBB03B57G069141"},
{"id":953,"car_make":"Nissan","car_model":"Frontier","year":1999,"vin":"KMHGH4JH3FU884550"},
{"id":954,"car_make":"Mercedes-Benz","car_model":"G-Class","year":2011,"vin":"JN8AZ1FY3EW700004"},
{"id":955,"car_make":"Chrysler","car_model":"Imperial","year":1926,"vin":"19UUA56983A506743"},
{"id":956,"car_make":"Chevrolet","car_model":"Camaro","year":1967,"vin":"WBAPH7C51BE620169"},
{"id":957,"car_make":"Maserati","car_model":"GranSport","year":2005,"vin":"4T1BF1FK3CU094843"},
{"id":958,"car_make":"Volkswagen","car_model":"Touareg 2","year":2009,"vin":"1G6DM5EG5A0740530"},
{"id":959,"car_make":"Pontiac","car_model":"Firebird","year":1993,"vin":"5UXZV4C56D0641391"},
{"id":960,"car_make":"Mitsubishi","car_model":"3000GT","year":1994,"vin":"WAULD64B44N256146"},
{"id":961,"car_make":"Subaru","car_model":"Impreza","year":1994,"vin":"1N6AD0CUXAC307812"},
{"id":962,"car_make":"Chevrolet","car_model":"Suburban 1500","year":2009,"vin":"JN1AJ0HP9AM905112"},
{"id":963,"car_make":"Acura","car_model":"RL","year":2011,"vin":"KMHCT4AEXDU244898"},
{"id":964,"car_make":"Mercury","car_model":"Topaz","year":1988,"vin":"WDDEJ7GB5CA395915"},
{"id":965,"car_make":"Hyundai","car_model":"Azera","year":2007,"vin":"JH4KB16697C039293"},
{"id":966,"car_make":"Geo","car_model":"Tracker","year":1993,"vin":"1G6AH5R3XE0273092"},
{"id":967,"car_make":"Toyota","car_model":"Highlander","year":2010,"vin":"1N6AA0CJ3DN080325"},
{"id":968,"car_make":"Mitsubishi","car_model":"Mirage","year":1988,"vin":"2C3CCAGG5EH759523"},
{"id":969,"car_make":"Mercedes-Benz","car_model":"Sprinter","year":2011,"vin":"JN8AE2KPXF9610136"},
{"id":970,"car_make":"Chevrolet","car_model":"Tahoe","year":2013,"vin":"SCFAB223X3K842131"},
{"id":971,"car_make":"GMC","car_model":"Canyon","year":2011,"vin":"1FMJK1JT3FE437721"},
{"id":972,"car_make":"Ford","car_model":"Lightning","year":1994,"vin":"5NPEB4AC6CH971513"},
{"id":973,"car_make":"Isuzu","car_model":"Amigo","year":1994,"vin":"3GYFNGEYXBS853370"},
{"id":974,"car_make":"Oldsmobile","car_model":"Achieva","year":1993,"vin":"JTHBL5EF8C5405281"},
{"id":975,"car_make":"Ford","car_model":"Explorer Sport Trac","year":2007,"vin":"1G6AB5SX9D0065251"},
{"id":976,"car_make":"Cadillac","car_model":"Eldorado","year":1996,"vin":"1FTEW1CW9AK186439"},
{"id":977,"car_make":"Lincoln","car_model":"MKT","year":2013,"vin":"5UXWX7C53DL156834"},
{"id":978,"car_make":"Cadillac","car_model":"XLR","year":2005,"vin":"WBALL5C51EE562702"},
{"id":979,"car_make":"Acura","car_model":"TL","year":1995,"vin":"1G6AP5SX8E0076485"},
{"id":980,"car_make":"Infiniti","car_model":"FX","year":2006,"vin":"2T2BK1BA5CC210680"},
{"id":981,"car_make":"Volkswagen","car_model":"Type 2","year":1991,"vin":"1GYUKJEF2AR760744"},
{"id":982,"car_make":"Lincoln","car_model":"Navigator","year":2000,"vin":"2T1BURHE2FC426207"},
{"id":983,"car_make":"Jeep","car_model":"Liberty","year":2009,"vin":"1D7RV1CT0BS391121"},
{"id":984,"car_make":"Toyota","car_model":"Highlander","year":2005,"vin":"WBANB33524B550381"},
{"id":985,"car_make":"Mercedes-Benz","car_model":"GL-Class","year":2009,"vin":"JM1CR2W34A0726669"},
{"id":986,"car_make":"Honda","car_model":"Civic","year":2001,"vin":"SCBLF34F42C063151"},
{"id":987,"car_make":"Lexus","car_model":"RX Hybrid","year":2006,"vin":"4T1BD1FK5EU485176"},
{"id":988,"car_make":"Oldsmobile","car_model":"Silhouette","year":1992,"vin":"WA1WMBFE9DD078976"},
{"id":989,"car_make":"Dodge","car_model":"D350 Club","year":1993,"vin":"3GTU1YEJ4BG288246"},
{"id":990,"car_make":"Mitsubishi","car_model":"Pajero","year":1998,"vin":"WBABS53433E521605"},
{"id":991,"car_make":"Ford","car_model":"Ranger","year":1994,"vin":"WBALM7C54AE667124"},
{"id":992,"car_make":"Acura","car_model":"RL","year":2002,"vin":"3N1CN7AP8FL855661"},
{"id":993,"car_make":"Mazda","car_model":"Familia","year":1992,"vin":"JHMFA3F28BS840910"},
{"id":994,"car_make":"Mercedes-Benz","car_model":"SL-Class","year":2003,"vin":"5J8TB18507A877011"},
{"id":995,"car_make":"Honda","car_model":"Civic","year":1992,"vin":"5N1AN0NU9AC245831"},
{"id":996,"car_make":"Buick","car_model":"Park Avenue","year":2003,"vin":"5UXWX7C55DL260516"},
{"id":997,"car_make":"Chevrolet","car_model":"1500","year":1993,"vin":"WAUDFAFL5BN923598"},
{"id":998,"car_make":"Oldsmobile","car_model":"Ciera","year":1994,"vin":"2T1BU4EE1DC969228"},
{"id":999,"car_make":"Buick","car_model":"Skyhawk","year":1985,"vin":"WAUJGAFD6FN070420"},
{"id":1000,"car_make":"Kia","car_model":"Carens","year":2009,"vin":"4JGCB2FE3CA205943"}]